{"meta":{"version":1,"warehouse":"4.0.0"},"models":{"Asset":[{"_id":"themes/sb-hitech/source/css/index.styl","path":"css/index.styl","modified":1,"renderable":1},{"_id":"themes/sb-hitech/source/css/var.styl","path":"css/var.styl","modified":1,"renderable":1},{"_id":"themes/sb-hitech/source/img/404.jpg","path":"img/404.jpg","modified":1,"renderable":1},{"_id":"themes/sb-hitech/source/img/algolia.svg","path":"img/algolia.svg","modified":1,"renderable":1},{"_id":"themes/sb-hitech/source/img/favicon.png","path":"img/favicon.png","modified":1,"renderable":1},{"_id":"themes/sb-hitech/source/img/friend_404.gif","path":"img/friend_404.gif","modified":1,"renderable":1},{"_id":"themes/sb-hitech/source/img/icp.png","path":"img/icp.png","modified":1,"renderable":1},{"_id":"themes/sb-hitech/source/img/loading.gif","path":"img/loading.gif","modified":1,"renderable":1},{"_id":"themes/sb-hitech/source/js/main.js","path":"js/main.js","modified":1,"renderable":1},{"_id":"themes/sb-hitech/source/js/tw_cn.js","path":"js/tw_cn.js","modified":1,"renderable":1},{"_id":"themes/sb-hitech/source/js/utils.js","path":"js/utils.js","modified":1,"renderable":1},{"_id":"themes/sb-hitech/source/js/search/algolia.js","path":"js/search/algolia.js","modified":1,"renderable":1},{"_id":"themes/sb-hitech/source/js/search/local-search.js","path":"js/search/local-search.js","modified":1,"renderable":1},{"_id":"source/assets/img/NHK.jpg","path":"assets/img/NHK.jpg","modified":1,"renderable":0},{"_id":"source/assets/img/Portraits.png","path":"assets/img/Portraits.png","modified":1,"renderable":0},{"_id":"source/assets/img/WeChatPay.jpg","path":"assets/img/WeChatPay.jpg","modified":1,"renderable":0},{"_id":"source/assets/img/favicon.jpg","path":"assets/img/favicon.jpg","modified":1,"renderable":0},{"_id":"source/assets/img/QQ/208934208 MF-COBOL招聘求职.PNG","path":"assets/img/QQ/208934208 MF-COBOL招聘求职.PNG","modified":1,"renderable":0},{"_id":"source/assets/img/QQ/212264777对日软件开发国内转职.png","path":"assets/img/QQ/212264777对日软件开发国内转职.png","modified":1,"renderable":0},{"_id":"source/assets/img/QQ/288460606 双创政策与产业园孵化.png","path":"assets/img/QQ/288460606 双创政策与产业园孵化.png","modified":1,"renderable":0},{"_id":"source/assets/img/QQ/330490168EDUBlockchain Basics.png","path":"assets/img/QQ/330490168EDUBlockchain Basics.png","modified":1,"renderable":0},{"_id":"source/assets/img/QQ/330511118创业·就职·公司交流 - 副本.png","path":"assets/img/QQ/330511118创业·就职·公司交流 - 副本.png","modified":1,"renderable":0},{"_id":"source/assets/img/QQ/330511118创业·就职·公司交流.png","path":"assets/img/QQ/330511118创业·就职·公司交流.png","modified":1,"renderable":0},{"_id":"source/assets/img/QQ/404380953.png","path":"assets/img/QQ/404380953.png","modified":1,"renderable":0},{"_id":"source/assets/img/QQ/445340268EDUBigData Basics.png","path":"assets/img/QQ/445340268EDUBigData Basics.png","modified":1,"renderable":0},{"_id":"source/assets/img/QQ/461886087 EDUSalesforce Basics.png","path":"assets/img/QQ/461886087 EDUSalesforce Basics.png","modified":1,"renderable":0},{"_id":"source/assets/img/QQ/68280758 上海财经大学研究生.png","path":"assets/img/QQ/68280758 上海财经大学研究生.png","modified":1,"renderable":0},{"_id":"source/assets/img/QQ/72287061 复旦大学研究生.png","path":"assets/img/QQ/72287061 复旦大学研究生.png","modified":1,"renderable":0},{"_id":"source/assets/img/QQ/73017515 西南财经大学研究生.png","path":"assets/img/QQ/73017515 西南财经大学研究生.png","modified":1,"renderable":0},{"_id":"source/assets/img/QQ/Salesforce开发@智跃职前实训群聊二维码.png","path":"assets/img/QQ/Salesforce开发@智跃职前实训群聊二维码.png","modified":1,"renderable":0},{"_id":"source/assets/img/QQ/大连东软信息学院本科群聊二维码.png","path":"assets/img/QQ/大连东软信息学院本科群聊二维码.png","modified":1,"renderable":0},{"_id":"source/assets/img/QQ/大连理工大学本科群聊二维码.png","path":"assets/img/QQ/大连理工大学本科群聊二维码.png","modified":1,"renderable":0},{"_id":"source/assets/img/QQ/大连理工大学研究生群聊二维码.png","path":"assets/img/QQ/大连理工大学研究生群聊二维码.png","modified":1,"renderable":0},{"_id":"source/assets/img/QQ/日本语学习交流@智跃职前实训群聊二维码.png","path":"assets/img/QQ/日本语学习交流@智跃职前实训群聊二维码.png","modified":1,"renderable":0},{"_id":"source/assets/img/QQ/智跃书店会员申请02群聊二维码 - 副本.png","path":"assets/img/QQ/智跃书店会员申请02群聊二维码 - 副本.png","modified":1,"renderable":0},{"_id":"source/assets/img/QQ/智跃书店会员申请02群聊二维码.png","path":"assets/img/QQ/智跃书店会员申请02群聊二维码.png","modified":1,"renderable":0},{"_id":"source/assets/img/QQ/ＮＨＫニュース2017下群聊二维码.png","path":"assets/img/QQ/ＮＨＫニュース2017下群聊二维码.png","modified":1,"renderable":0},{"_id":"source/assets/img/QQ/ＮＨＫニュース2018上群聊二维码.png","path":"assets/img/QQ/ＮＨＫニュース2018上群聊二维码.png","modified":1,"renderable":0},{"_id":"source/assets/img/dingding/dingding-circle-career.jpg","path":"assets/img/dingding/dingding-circle-career.jpg","modified":1,"renderable":0},{"_id":"source/assets/img/dingding/dingding-circle-learning.jpg","path":"assets/img/dingding/dingding-circle-learning.jpg","modified":1,"renderable":0},{"_id":"source/assets/img/dingding/dingding-circle-study.jpg","path":"assets/img/dingding/dingding-circle-study.jpg","modified":1,"renderable":0},{"_id":"source/assets/img/dingding/dingding-group-business-it.jpg","path":"assets/img/dingding/dingding-group-business-it.jpg","modified":1,"renderable":0},{"_id":"source/assets/img/dingding/dingding-group-excle-rpa.jpg","path":"assets/img/dingding/dingding-group-excle-rpa.jpg","modified":1,"renderable":0},{"_id":"source/assets/img/dingding/dingding-group-help.jpg","path":"assets/img/dingding/dingding-group-help.jpg","modified":1,"renderable":0},{"_id":"source/assets/img/dingding/dingding-group-itjapanese-practice.jpg","path":"assets/img/dingding/dingding-group-itjapanese-practice.jpg","modified":1,"renderable":0},{"_id":"source/assets/img/dingding/dingding-group-japanese-music.jpg","path":"assets/img/dingding/dingding-group-japanese-music.jpg","modified":1,"renderable":0},{"_id":"source/assets/img/dingding/dingding-group-life.jpg","path":"assets/img/dingding/dingding-group-life.jpg","modified":1,"renderable":0},{"_id":"source/assets/img/dingding/dingding-group-mainframe.jpg","path":"assets/img/dingding/dingding-group-mainframe.jpg","modified":1,"renderable":0},{"_id":"source/assets/img/dingding/dingding-group-resume-homepage.jpg","path":"assets/img/dingding/dingding-group-resume-homepage.jpg","modified":1,"renderable":0},{"_id":"source/assets/img/dingding/dingding-group-salesforce.jpg","path":"assets/img/dingding/dingding-group-salesforce.jpg","modified":1,"renderable":0},{"_id":"source/assets/img/top/1.jpg","path":"assets/img/top/1.jpg","modified":1,"renderable":0},{"_id":"source/assets/img/top/2.jpg","path":"assets/img/top/2.jpg","modified":1,"renderable":0},{"_id":"source/assets/img/top/3.jpg","path":"assets/img/top/3.jpg","modified":1,"renderable":0},{"_id":"source/assets/img/top/4.jpg","path":"assets/img/top/4.jpg","modified":1,"renderable":0},{"_id":"source/assets/img/top/5.jpg","path":"assets/img/top/5.jpg","modified":1,"renderable":0},{"_id":"source/assets/img/top/6.jpg","path":"assets/img/top/6.jpg","modified":1,"renderable":0},{"_id":"source/assets/img/top/7.jpg","path":"assets/img/top/7.jpg","modified":1,"renderable":0},{"_id":"source/assets/img/top/8.jpg","path":"assets/img/top/8.jpg","modified":1,"renderable":0},{"_id":"source/assets/img/top/9.jpg","path":"assets/img/top/9.jpg","modified":1,"renderable":0}],"Cache":[{"_id":"source/index.md","hash":"da7897ce19accb32d49b364ce8bad03004c423d1","modified":1604387394883},{"_id":"source/business-policy/index.md","hash":"92ee0685f73518fbaeecaae2c680deff246fff60","modified":1604387394883},{"_id":"source/categories/index.md","hash":"5f88af47e7f314de2480f783278fe19c1e7a1c7d","modified":1604387394883},{"_id":"source/about/index.md","hash":"5aec9e1a84f69876babfd6fddfabc29505121b2d","modified":1604387394703},{"_id":"source/link/index.md","hash":"75a73725415ac41fcf76ad0148aa08786495a8b0","modified":1604453735680},{"_id":"source/copyright-policy/index.md","hash":"a5f1477fd27f8d3c964388c939111f68c025c00a","modified":1604453539390},{"_id":"source/movies/index.md","hash":"de919cd4993313cbe43738a0810266aaceb61456","modified":1604387394893},{"_id":"source/music/index.md","hash":"8236006842388dd7f6d6e8d9041764692a044530","modified":1604387394893},{"_id":"source/privacy-policy/index.md","hash":"6591bfdf114399a585b6c183c8c7bf2dccfff2f3","modified":1604387394903},{"_id":"source/tags/index.md","hash":"e08fa7e6bfdfd96dad3716bdc6a20846bc781224","modified":1604387394903},{"_id":"source/_posts/ja/Resume.md","hash":"08769e7ea2072324d327edd77432cfb3c230b8b9","modified":1606885925100},{"_id":"source/assets/img/NHK.jpg","hash":"7b4510f981f51b1104b40efa1e352aa996921708","modified":1604387394703},{"_id":"source/assets/img/Portraits.png","hash":"279a3004e12e0489fc21727117aa6655a1f9819b","modified":1604387394703},{"_id":"source/assets/img/favicon.jpg","hash":"7007a1189813e264177c4ef89b61b2ba22adc9a6","modified":1604387394823},{"_id":"source/assets/img/QQ/208934208 MF-COBOL招聘求职.PNG","hash":"1bad87f77de71d04f70029ef2b591e9c29e55a1f","modified":1604387394713},{"_id":"source/assets/img/QQ/212264777对日软件开发国内转职.png","hash":"7a614fdc54eed1ed838163a8bd69777d8df959d2","modified":1604387394713},{"_id":"source/assets/img/QQ/288460606 双创政策与产业园孵化.png","hash":"d4989012114a67165f1e9f088013c5565d0369b9","modified":1604387394713},{"_id":"source/assets/img/QQ/330490168EDUBlockchain Basics.png","hash":"6ef2be030d1ef8df7ddcd9801ad22d25b7b0bc7d","modified":1604387394713},{"_id":"source/assets/img/QQ/330511118创业·就职·公司交流 - 副本.png","hash":"a21d50ca6d12d3fcacb7199ce3960801f4af2a24","modified":1604387394723},{"_id":"source/assets/img/QQ/330511118创业·就职·公司交流.png","hash":"87bd19e9e5df264a2ab16af27dc74c79d9f1fc3f","modified":1604387394723},{"_id":"source/assets/img/QQ/404380953.png","hash":"9cb4d4ed8fdfc7e8fc3ddd2f17faf982ee5ca58d","modified":1604387394723},{"_id":"source/assets/img/QQ/445340268EDUBigData Basics.png","hash":"dd14fac59d62afa50c68d6f90c8fed10c6584231","modified":1604387394733},{"_id":"source/assets/img/QQ/461886087 EDUSalesforce Basics.png","hash":"a17ad7ad7c608927398362b966c48c5594cbd349","modified":1604387394733},{"_id":"source/assets/img/QQ/68280758 上海财经大学研究生.png","hash":"ecda46ecd209240d9abe1c7eb439e24fea19df6c","modified":1604387394733},{"_id":"source/assets/img/QQ/72287061 复旦大学研究生.png","hash":"42875f61890bcce9e9f096443e7ec973b76452f0","modified":1604387394743},{"_id":"source/assets/img/QQ/73017515 西南财经大学研究生.png","hash":"31f6e56871c15689c2389495f007c6360d09d940","modified":1604387394743},{"_id":"source/assets/img/QQ/Salesforce开发@智跃职前实训群聊二维码.png","hash":"fd47d9cd84e42c7ae995608be699e80b13331523","modified":1604387394743},{"_id":"source/assets/img/QQ/大连东软信息学院本科群聊二维码.png","hash":"f93c6d6e19b346e4c07484fd7b52151086f1f5e8","modified":1604387394743},{"_id":"source/assets/img/QQ/大连理工大学本科群聊二维码.png","hash":"a0777e92aedc9f96df4efee1014477c44b1c40be","modified":1604387394743},{"_id":"source/assets/img/QQ/大连理工大学研究生群聊二维码.png","hash":"02360b2cc975224cbe6b3f919506d6554989f869","modified":1604387394753},{"_id":"source/assets/img/QQ/日本语学习交流@智跃职前实训群聊二维码.png","hash":"4326e037bc6ce0789fefd9fcd122ca770b9c9b65","modified":1604387394753},{"_id":"source/assets/img/QQ/智跃书店会员申请02群聊二维码 - 副本.png","hash":"fa7506fdef2cfcd2d28ee9067dfda7c887fb8802","modified":1604387394753},{"_id":"source/assets/img/QQ/智跃书店会员申请02群聊二维码.png","hash":"c6117b22920ef4481aadc169aafa69b291cedc6e","modified":1604387394753},{"_id":"source/assets/img/QQ/ＮＨＫニュース2017下群聊二维码.png","hash":"6f5a8bcdfd8cde2cd83d4583704c459daa42ee49","modified":1604387394763},{"_id":"source/assets/img/QQ/ＮＨＫニュース2018上群聊二维码.png","hash":"dcab28446e552b3e32beb25463b888dcd00724de","modified":1604387394763},{"_id":"source/assets/img/top/3.jpg","hash":"3af041668a04939ea051dec6a911148ca6e5c46b","modified":1604387394843},{"_id":"source/assets/img/WeChatPay.jpg","hash":"e02421797e0c699c728604eea5c60c5b759132d1","modified":1604387394763},{"_id":"source/assets/img/dingding/dingding-circle-career.jpg","hash":"d0f520565b6b411b1359d528d2cafac5581aec47","modified":1604387394773},{"_id":"source/assets/img/dingding/dingding-circle-learning.jpg","hash":"cae36f3016bca8bac52c9eec97606272e9f4e548","modified":1604387394773},{"_id":"source/assets/img/dingding/dingding-circle-study.jpg","hash":"acff588ecda7439ce6ce57640eea4e6bd5e6343b","modified":1604387394783},{"_id":"source/_posts/ja/Resume/Resume_Shubin_Sun_JA_PR_20210101.pdf","hash":"4c3af1f358859af086a8c1c93be608d808b2b91d","modified":1606196744854},{"_id":"source/assets/img/dingding/dingding-group-business-it.jpg","hash":"7fcc5d15171d6e37a00c52bd91d2739f15208369","modified":1604387394783},{"_id":"source/assets/img/dingding/dingding-group-excle-rpa.jpg","hash":"5ab1379a028d35802b22233b9b1f462a8d05bd52","modified":1604387394793},{"_id":"source/assets/img/dingding/dingding-group-help.jpg","hash":"1f600bf2396e7f78f7390a090de306c373e6d2b3","modified":1604387394793},{"_id":"source/assets/img/dingding/dingding-group-itjapanese-practice.jpg","hash":"ed260c7b2c5df51bd9c89c7e8bc327acd8e80d87","modified":1604387394803},{"_id":"source/assets/img/dingding/dingding-group-japanese-music.jpg","hash":"ed10115f89ea6531fb34264aecdfbe8787662b49","modified":1604387394803},{"_id":"source/assets/img/dingding/dingding-group-life.jpg","hash":"858eda31e4b17a8fc778c7a75645f312293763f7","modified":1604387394813},{"_id":"source/assets/img/dingding/dingding-group-mainframe.jpg","hash":"28800f6679f6ec8ee223ff5b7dc3bea63a6066ca","modified":1604387394813},{"_id":"source/assets/img/dingding/dingding-group-resume-homepage.jpg","hash":"0e5f5eb7de70a3942d7c947a772045eb35fa83a2","modified":1604387394823},{"_id":"source/assets/img/dingding/dingding-group-salesforce.jpg","hash":"09e6aacad1ec3d12a34d282835c820e2c7f98981","modified":1604387394823},{"_id":"source/assets/img/top/7.jpg","hash":"f7cda1c0c09731ef8bb2e2cb1c299e0529a08e78","modified":1604387394853},{"_id":"source/assets/img/top/8.jpg","hash":"8e1ea131267d6898a4fbdfb85ee57d57d9b96481","modified":1604387394863},{"_id":"themes/sb-hitech/LICENSE","hash":"c8bc7df08db9dd3b39c2c2259a163a36cf2f6808","modified":1604387233872},{"_id":"themes/sb-hitech/README.md","hash":"7492ec8d055f4c49dcca86f9d81f6c719bd53ac9","modified":1604387233875},{"_id":"themes/sb-hitech/README_CN.md","hash":"566ea1d5c3137f455b28a3f75941abb265cd4140","modified":1604387233877},{"_id":"themes/sb-hitech/package.json","hash":"72705c927abe1d76ed242decff37f804b7eef031","modified":1604387234253},{"_id":"themes/sb-hitech/_config.yml","hash":"642c1acad3802dfd96d3a2d32d503f70401e2989","modified":1604636555777},{"_id":"themes/sb-hitech/layout/archive.pug","hash":"2d5bf4b1755f89898c579c18d601be83d2bc8ebd","modified":1604387233904},{"_id":"themes/sb-hitech/layout/404.pug","hash":"10ce9b0764d975460069bf116bfceaaeb9691d3a","modified":1604387233900},{"_id":"themes/sb-hitech/layout/category.pug","hash":"90e56274a7c853f6f30337011f9c9d6d035950dc","modified":1604387233909},{"_id":"themes/sb-hitech/layout/index.pug","hash":"648dcbdb3d145a710de81c909e000e8664d2ac9c","modified":1604387234239},{"_id":"themes/sb-hitech/layout/page.pug","hash":"76536c903cabc8e4619759e3a8b6a384c0518716","modified":1604387234240},{"_id":"themes/sb-hitech/layout/post.pug","hash":"ec479a98b752a6ec47ec62e932c59275d5c344b1","modified":1604387234242},{"_id":"themes/sb-hitech/layout/tag.pug","hash":"4bb5efc6dabdf1626685bf6771aaa1467155ae86","modified":1604387234251},{"_id":"themes/sb-hitech/languages/default.yml","hash":"02349c0728bbf723ce23c4fed46a6ea68f84e752","modified":1604387233887},{"_id":"themes/sb-hitech/languages/en.yml","hash":"02349c0728bbf723ce23c4fed46a6ea68f84e752","modified":1604387233889},{"_id":"themes/sb-hitech/languages/zh-CN.yml","hash":"0df1a9d6d542d0ac354098ee7d3cd65d96f75409","modified":1604387233893},{"_id":"themes/sb-hitech/languages/zh-TW.yml","hash":"21eaedd8813476b1cca2bf098c61df493b23abef","modified":1604387233897},{"_id":"themes/sb-hitech/layout/includes/additional-js.pug","hash":"62b02e90b566259e3c18af85014f2acaaa2fe278","modified":1604387233934},{"_id":"themes/sb-hitech/layout/includes/footer.pug","hash":"e6f4f13ff68cc0d4fe2721024d9663a4a534ce6f","modified":1604452918214},{"_id":"themes/sb-hitech/layout/includes/head.pug","hash":"093e018a094dce27ceb493a09bbc4e5d1682a844","modified":1604387233939},{"_id":"themes/sb-hitech/layout/includes/layout.pug","hash":"6006ae4885ad82bd41ffd0f1734bde94d442c9ff","modified":1604387233982},{"_id":"themes/sb-hitech/layout/includes/pagination.pug","hash":"ef9a7bc996a08f1aa939cdb6df03084b0ea6c9dd","modified":1604387234018},{"_id":"themes/sb-hitech/layout/includes/rightside.pug","hash":"975ce0b43c819a877399fd1713b7648b6a65bd71","modified":1604387234026},{"_id":"themes/sb-hitech/scripts/events/404.js","hash":"5f6127ede7d139891208340b5cf5bf9314e4be7d","modified":1604387234259},{"_id":"themes/sb-hitech/layout/includes/sidebar.pug","hash":"86b2a4d500542fe764fdc5ff71cf029604325930","modified":1604387234030},{"_id":"themes/sb-hitech/scripts/events/init.js","hash":"f7ab55363d05c945569d9ac4afc889f9706308c6","modified":1604387234261},{"_id":"themes/sb-hitech/scripts/events/welcome.js","hash":"1e1da036fae593be7e2cc502f0a5cbeb2e7881d1","modified":1604387234263},{"_id":"themes/sb-hitech/scripts/filters/post_lazyload.js","hash":"1e2ac4d26df7cd18a92f1404329f8eb1c388dc18","modified":1604387234266},{"_id":"themes/sb-hitech/scripts/filters/random_cover.js","hash":"dbce193ba170e004790550fe4694de8e29b299b9","modified":1604387234268},{"_id":"themes/sb-hitech/scripts/helpers/aside_archives.js","hash":"d9cdeecfb0098ad9bf4814ea2f95167b637e015d","modified":1604387234272},{"_id":"themes/sb-hitech/scripts/helpers/aside_categories.js","hash":"5060ef561013dc036ec569f77521d5dab894db73","modified":1604387234274},{"_id":"themes/sb-hitech/scripts/helpers/page.js","hash":"f42b2358a44d91ef6c853ce75f23af6e8d3ff423","modified":1604387234284},{"_id":"themes/sb-hitech/scripts/helpers/related_post.js","hash":"0745597f4ffadde037e57e0f66f7d984dc576dc6","modified":1604387234294},{"_id":"themes/sb-hitech/scripts/tag/button.js","hash":"54c0c9c6d4d4ca754680cd24d7e204a745a6eec0","modified":1604387234303},{"_id":"themes/sb-hitech/scripts/tag/gallery.js","hash":"90e9d5f499c791225a257f062886fedec5973b18","modified":1604387234305},{"_id":"themes/sb-hitech/scripts/tag/hide.js","hash":"a3c3c3feafa544304c1beeb90d25022170a32643","modified":1604387234307},{"_id":"themes/sb-hitech/scripts/tag/mermaid.js","hash":"829229b0074b332ba779e159219eb2466612ff6e","modified":1604387234309},{"_id":"themes/sb-hitech/scripts/tag/note.js","hash":"420ba8b11e7316b4c09eb301d39814bc9bae9f90","modified":1604387234313},{"_id":"themes/sb-hitech/scripts/tag/tabs.js","hash":"296e17f28d45f85ea638fbc5bc0b6e8e002924aa","modified":1604387234315},{"_id":"themes/sb-hitech/source/css/index.styl","hash":"9a13b40cf4b79980f49a2578cb2c35c04b7f5618","modified":1604387234647},{"_id":"themes/sb-hitech/source/css/var.styl","hash":"ae8193bd0107c823b8d2a123f1c301084c9c227a","modified":1604387234669},{"_id":"themes/sb-hitech/source/img/404.jpg","hash":"fb4489bc1d30c93d28f7332158c1c6c1416148de","modified":1604387234672},{"_id":"themes/sb-hitech/source/img/algolia.svg","hash":"45eeea0b5fba833e21e38ea10ed5ab385ceb4f01","modified":1604387234675},{"_id":"themes/sb-hitech/source/img/favicon.png","hash":"3cf89864b4f6c9b532522a4d260a2e887971c92d","modified":1604387234677},{"_id":"themes/sb-hitech/source/img/friend_404.gif","hash":"8d2d0ebef70a8eb07329f57e645889b0e420fa48","modified":1604387234680},{"_id":"themes/sb-hitech/source/img/icp.png","hash":"cb1fd69b38ec23ce8366668ddffbbd0160de0104","modified":1604387234682},{"_id":"themes/sb-hitech/source/img/loading.gif","hash":"5f0287fb8fb98872fe1998c6f781111819e71806","modified":1604387234685},{"_id":"themes/sb-hitech/source/js/main.js","hash":"bad76aecdfc0181fb06dc5dd80a5f6fbca6fa44d","modified":1604387234689},{"_id":"themes/sb-hitech/source/js/tw_cn.js","hash":"81952d4744af55a9e123c57fd8e0004d345d7352","modified":1604387234697},{"_id":"themes/sb-hitech/source/js/utils.js","hash":"fb39c008221509c9c57744fe75c1bcaf005a5d43","modified":1604387234699},{"_id":"themes/sb-hitech/layout/includes/head/analytics.pug","hash":"25fdae675275d2cefe427c6b5c3f73ed72c6bfbf","modified":1604387233945},{"_id":"themes/sb-hitech/layout/includes/head/Open_Graph.pug","hash":"767b425f97e74a98002f4a435e36e8ec27e8a994","modified":1604387233942},{"_id":"themes/sb-hitech/layout/includes/head/config.pug","hash":"ed8810709c060691c2000f23f3509e840e239444","modified":1604387233948},{"_id":"themes/sb-hitech/layout/includes/head/config_site.pug","hash":"7465f46abba307180d0605dc175eb857f9abe57a","modified":1604387233950},{"_id":"themes/sb-hitech/layout/includes/head/google_adsense.pug","hash":"f29123e603cbbcc6ce277d4e8f600ba67498077c","modified":1604387233953},{"_id":"themes/sb-hitech/layout/includes/head/js.pug","hash":"0916746e3f0ba8aee4defa6e6244752618721461","modified":1604387233954},{"_id":"themes/sb-hitech/layout/includes/head/noscript.pug","hash":"72efaa09ff60843567458bd54152e06f0cb2757e","modified":1604387233956},{"_id":"themes/sb-hitech/layout/includes/head/preconnect.pug","hash":"59844b533b1f633e1cad4c7f7d79536429bc3d2c","modified":1604387233958},{"_id":"themes/sb-hitech/layout/includes/head/pwa.pug","hash":"6dc2c9b85df9ab4f5b554305339fd80a90a6cf43","modified":1604387233959},{"_id":"themes/sb-hitech/layout/includes/head/site_verification.pug","hash":"1ddbd09e1902da7fa4bf7824654f132e41622c42","modified":1604387233962},{"_id":"themes/sb-hitech/layout/includes/header/index.pug","hash":"9a6f8211cdcb4aa87ccb5fa4f62b89c245412c94","modified":1604387233966},{"_id":"themes/sb-hitech/layout/includes/header/menu_item.pug","hash":"d22d4c98028272dfc6c2e721e469f572a6b62ed3","modified":1604387233972},{"_id":"themes/sb-hitech/layout/includes/header/nav.pug","hash":"a6eef85736af51d08a794fde00d1a9a8ef566d89","modified":1604387233974},{"_id":"themes/sb-hitech/layout/includes/header/social.pug","hash":"631ec7000fd4d6cfa2de118ee02ad8a42ffb34f5","modified":1604387233979},{"_id":"themes/sb-hitech/layout/includes/header/post-info.pug","hash":"a12b7788b80d2337cd5788fa74ccb701a8dd963e","modified":1604387233977},{"_id":"themes/sb-hitech/layout/includes/loading/loading-js.pug","hash":"81a34e9d642a68e77650609601a8096c6445daef","modified":1604387233988},{"_id":"themes/sb-hitech/layout/includes/loading/loading.pug","hash":"dd8e6813976be64e80eba6562b54e74527ab306d","modified":1604387233992},{"_id":"themes/sb-hitech/layout/includes/mixins/article-sort.pug","hash":"2beb27e33e4492fa80e88c37dcb7a3ffd7da9e24","modified":1604387233996},{"_id":"themes/sb-hitech/layout/includes/mixins/post-ui.pug","hash":"9ac6e803603a67ec3f61fc0e98ae8d4fe9c6c8a7","modified":1604387233998},{"_id":"themes/sb-hitech/layout/includes/page/artitalk.pug","hash":"006309e66180a521289dddae9d2aa3b37bc3492f","modified":1604387234004},{"_id":"themes/sb-hitech/layout/includes/page/categories.pug","hash":"95924d28d71b28769963529f82b376a9dc731fad","modified":1604387234006},{"_id":"themes/sb-hitech/layout/includes/page/default-page.pug","hash":"f5ea1e10a169aeb98e42b19ac084c4eb27693b46","modified":1604387234009},{"_id":"themes/sb-hitech/layout/includes/page/flink.pug","hash":"7e7832aafdf5ca50e71a039ad3fc98d8ef6e7d30","modified":1604387234011},{"_id":"themes/sb-hitech/layout/includes/page/tags.pug","hash":"62dc2e683d56ddc9b588abc44dc1cfb778a2c68f","modified":1604387234014},{"_id":"themes/sb-hitech/layout/includes/post/reward.pug","hash":"d9b96f24c2439f263a606fd38a5517bd4bb162b7","modified":1604387234024},{"_id":"themes/sb-hitech/layout/includes/post/post-copyright.pug","hash":"ebdf754ecee004d3cc040c92d82dda06f08ead03","modified":1604453006640},{"_id":"themes/sb-hitech/layout/includes/third-party/aplayer.pug","hash":"eb18647e15acbf0f9faf9c56bc43cecc6c3069b1","modified":1604387234034},{"_id":"themes/sb-hitech/layout/includes/third-party/artitalk.pug","hash":"99fb65c54a687b76e14f517ffb5dd2f607e0e5ed","modified":1604387234036},{"_id":"themes/sb-hitech/layout/includes/third-party/baidu_push.pug","hash":"f23428ac998c9844e616fa19113dd35a601538ae","modified":1604387234038},{"_id":"themes/sb-hitech/layout/includes/third-party/pangu.pug","hash":"c7d65a5376b04e385d4b725c018f94ea40d0bf06","modified":1604387234173},{"_id":"themes/sb-hitech/layout/includes/third-party/effect.pug","hash":"827590914284c10903107a406fddd9f9cd0b4c11","modified":1604387234099},{"_id":"themes/sb-hitech/layout/includes/third-party/pjax.pug","hash":"8343f868dd31ccc080d499e5e95a8fc01dc811fa","modified":1604387234175},{"_id":"themes/sb-hitech/layout/includes/third-party/prismjs.pug","hash":"2448b243ded58aa1d5fc22fd115e6d06b636f9fd","modified":1604387234177},{"_id":"themes/sb-hitech/layout/includes/widget/card_ad.pug","hash":"44af3c7a67b86f048deacb451dd454b088631374","modified":1604387234203},{"_id":"themes/sb-hitech/layout/includes/third-party/subtitle.pug","hash":"b210ae4e1c53b5a99216a6a75d100fc63b2bb65b","modified":1604387234199},{"_id":"themes/sb-hitech/layout/includes/widget/card_announcement.pug","hash":"7450c5bae8aa422c39504a3574f97ef1709d1779","modified":1604387234205},{"_id":"themes/sb-hitech/layout/includes/widget/card_archives.pug","hash":"59d1096a1bb04c9559367d54d90186afcc115850","modified":1604387234207},{"_id":"themes/sb-hitech/layout/includes/widget/card_author.pug","hash":"b592c39e7ca61847b5a5629768bb44690802185d","modified":1604387234209},{"_id":"themes/sb-hitech/layout/includes/widget/card_categories.pug","hash":"40923d59c452d2a71195ddf1a8e3b840f27ef560","modified":1604387234211},{"_id":"themes/sb-hitech/layout/includes/widget/card_newest_comment.pug","hash":"2254c7ae4ad45be850e1777035d084b1d31885fc","modified":1604387234213},{"_id":"themes/sb-hitech/layout/includes/widget/card_post_toc.pug","hash":"1b48347561b6d068f3c720802dd9223a8d1971a5","modified":1604387234215},{"_id":"themes/sb-hitech/layout/includes/widget/card_recent_post.pug","hash":"d4d50735c3678c4474cd4eec6050024ff9123458","modified":1604387234218},{"_id":"themes/sb-hitech/layout/includes/widget/card_tags.pug","hash":"b68b218472ef668890ab1207b1d9c15a9f2b585a","modified":1604387234220},{"_id":"themes/sb-hitech/layout/includes/widget/card_webinfo.pug","hash":"a701dab84ef06177a3baf91f31a9e4cb9a2e967a","modified":1604387234231},{"_id":"themes/sb-hitech/layout/includes/widget/index.pug","hash":"60b308f6e2fe3e78fd9dfbbc874989fdae38fd30","modified":1604387234236},{"_id":"themes/sb-hitech/source/css/_highlight/highlight.styl","hash":"536b6b987ea9371d6a960a693aee36147d523efc","modified":1604387234337},{"_id":"themes/sb-hitech/source/css/_highlight/theme.styl","hash":"3f0b8699f529f0842c3b101006f60cb7933c16ff","modified":1604387234390},{"_id":"themes/sb-hitech/source/css/_global/function.styl","hash":"1024193a42e1e36930f7361a019022de59fe735c","modified":1604387234327},{"_id":"themes/sb-hitech/source/css/_global/index.styl","hash":"125d2aee370ab07755fe4cb00decc53619be17f8","modified":1604387234329},{"_id":"themes/sb-hitech/source/css/_layout/404.styl","hash":"84c14368d3fab66d5fb7d03678766274e2e0d84f","modified":1604387234396},{"_id":"themes/sb-hitech/source/css/_layout/aside.styl","hash":"c03a1b8b9db59a94cadd1dfc7e779ca97e713c37","modified":1604387234400},{"_id":"themes/sb-hitech/source/css/_layout/chat.styl","hash":"f27ad7b5d781c98bcac5c12c2d70b69b830e0374","modified":1604387234403},{"_id":"themes/sb-hitech/source/css/_layout/comments.styl","hash":"8e6c9a2c1881985e4b2ae14ef1bdfdbb1bc83b37","modified":1604387234407},{"_id":"themes/sb-hitech/source/css/_layout/footer.styl","hash":"473d2a6c11f7ff82b28923ddece95919d136d310","modified":1604387234410},{"_id":"themes/sb-hitech/source/css/_layout/head.styl","hash":"a424da04c2a0c7e6a27bee4a3aef41be25307ee6","modified":1604387234412},{"_id":"themes/sb-hitech/source/css/_layout/loading.styl","hash":"807f18717c29b5c41de6fc600a69a80ce8b7a19c","modified":1604387234415},{"_id":"themes/sb-hitech/source/css/_layout/pagination.styl","hash":"c4ae9292d6b7e42943b1b11e109ed560dc3a7753","modified":1604387234449},{"_id":"themes/sb-hitech/source/css/_layout/post.styl","hash":"c68a3b9c386a52219e61eb404523d4f13060c07b","modified":1604387234451},{"_id":"themes/sb-hitech/source/css/_layout/relatedposts.styl","hash":"ba391266cd967fa96109677455dd6701292afd52","modified":1604387234457},{"_id":"themes/sb-hitech/source/css/_layout/reward.styl","hash":"d6149c50ad33b3feb3da8a9d0b9e6557d1137210","modified":1604387234459},{"_id":"themes/sb-hitech/source/css/_layout/rightside.styl","hash":"7a37f7ffeb17ea4fc7765e0ee13fb81850d28554","modified":1604387234461},{"_id":"themes/sb-hitech/source/css/_layout/sidebar.styl","hash":"78ef182c0f6711c8491a8ee421b708c8f2a63c30","modified":1604387234463},{"_id":"themes/sb-hitech/source/css/_layout/third-party.styl","hash":"0cb678f991af06015804eaebafa8e983b0dcc3de","modified":1604387234465},{"_id":"themes/sb-hitech/source/css/_mode/darkmode.styl","hash":"d471c8192e6c9f686daeca61527d627e8da08551","modified":1604387234469},{"_id":"themes/sb-hitech/source/css/_mode/readmode.styl","hash":"39750c1aef1671d0efa6421a53fb2bfd818b28c5","modified":1604387234471},{"_id":"themes/sb-hitech/source/css/_page/archives.styl","hash":"190b85de3e686393e45869d12464995f23b304dc","modified":1604387234477},{"_id":"themes/sb-hitech/source/css/_page/categories.styl","hash":"ca1d3a885a85a91fcd6f7b55fca96cafb6a1b0a3","modified":1604387234481},{"_id":"themes/sb-hitech/source/css/_page/common.styl","hash":"4058ab759577efe280d5e38902be39054ed4b471","modified":1604387234483},{"_id":"themes/sb-hitech/source/css/_page/flink.styl","hash":"3c7a7efbb14d8ce6538f612992aa1a62fd278991","modified":1604387234487},{"_id":"themes/sb-hitech/source/css/_page/homepage.styl","hash":"66fd9cab11a5ec7591b8d48e64a26cf576a69cd7","modified":1604387234525},{"_id":"themes/sb-hitech/source/css/_page/tags.styl","hash":"26e26797b3175498e20b2a8bf1679d3ed9fac5a6","modified":1604387234529},{"_id":"themes/sb-hitech/source/css/_search/algolia.styl","hash":"a470029a157fbb8406ff72322a75ef63d6675431","modified":1604387234570},{"_id":"themes/sb-hitech/source/css/_search/index.styl","hash":"202b01db6ef3cca9e5a173e1a0dadfee8854a849","modified":1604387234572},{"_id":"themes/sb-hitech/source/css/_search/local-search.styl","hash":"3f2e0b3c9158ea5ceaf46486666ade3ed9752fed","modified":1604387234574},{"_id":"themes/sb-hitech/source/css/_tags/button.styl","hash":"5fe4235c038ed128819bd6918cd0781b372b598e","modified":1604387234617},{"_id":"themes/sb-hitech/source/css/_tags/gallery.styl","hash":"a5fcce868c93c073ae2f555ace46a78f72c70067","modified":1604387234621},{"_id":"themes/sb-hitech/source/css/_tags/hexo.styl","hash":"aa0728c556af75f5d66ecd44fa207722d474c26d","modified":1604387234624},{"_id":"themes/sb-hitech/source/css/_tags/hide.styl","hash":"8ab69f23ee331317abccafbc26943cfbae961ecc","modified":1604387234627},{"_id":"themes/sb-hitech/source/css/_tags/note.styl","hash":"75a5c15c7029197ec5cffd27f7c5455891c946c9","modified":1604387234629},{"_id":"themes/sb-hitech/source/css/_tags/tabs.styl","hash":"8520674768dd0b1837f947892e8402b192a4f9c1","modified":1604387234633},{"_id":"themes/sb-hitech/source/css/_third-party/normalize.min.css","hash":"8549829fb7d3c21cd9e119884962e8c463a4a267","modified":1604387234644},{"_id":"themes/sb-hitech/source/js/search/algolia.js","hash":"bde8bbc75dfa0eaa512af498046a85660a56d3de","modified":1604387234692},{"_id":"themes/sb-hitech/source/js/search/local-search.js","hash":"5f3d48f61f10c0da538d54643edc47c0ccaa4d8e","modified":1604387234695},{"_id":"themes/sb-hitech/layout/includes/third-party/chat/crisp.pug","hash":"b741b5e942481d779a8a1fe94c45154a62a6b748","modified":1604387234047},{"_id":"themes/sb-hitech/layout/includes/third-party/chat/chatra.pug","hash":"f3f6eaecbcf9352342e259f4a5a3ad7160f31fc9","modified":1604387234042},{"_id":"themes/sb-hitech/layout/includes/third-party/chat/daovoice.pug","hash":"e5af55cdb87d1ffd3d8702bc77097159acf95b54","modified":1604387234048},{"_id":"themes/sb-hitech/layout/includes/third-party/chat/gitter.pug","hash":"794ce3911f17d354b7196deb8c36d191afac63fb","modified":1604387234053},{"_id":"themes/sb-hitech/layout/includes/third-party/chat/index.pug","hash":"bb467bb22f3d0775b33f9eacbfc086ecb7831e78","modified":1604387234055},{"_id":"themes/sb-hitech/layout/includes/third-party/chat/tidio.pug","hash":"cd7ab4a776be93eea96a6f6fd0a547977fbe1ea3","modified":1604387234057},{"_id":"themes/sb-hitech/layout/includes/third-party/comments/disqus.pug","hash":"663a298253eddb5126ca1a6139d69c7097ffb52e","modified":1604387234061},{"_id":"themes/sb-hitech/layout/includes/third-party/comments/disqusjs.pug","hash":"b4ccb07da181513ac6b2aa2ad8386b0275def87c","modified":1604387234063},{"_id":"themes/sb-hitech/layout/includes/third-party/comments/facebook_comments.pug","hash":"9b6b7b589ef7a8109d88ba439b2d8baf7286b961","modified":1604387234066},{"_id":"themes/sb-hitech/layout/includes/third-party/comments/gitalk.pug","hash":"35e25b7627c158a25e56b8fb5e47fb4dd751f7e0","modified":1604387234068},{"_id":"themes/sb-hitech/layout/includes/third-party/comments/index.pug","hash":"0f06c0aa7538b41554689d2298556fece6dfd1de","modified":1604387234071},{"_id":"themes/sb-hitech/layout/includes/third-party/comments/js.pug","hash":"6f4829a8e08c3bd36e96477efdbe552c85a7350b","modified":1604387234074},{"_id":"themes/sb-hitech/layout/includes/third-party/comments/livere.pug","hash":"589f8503f264d4fda971c8daf2028f45c4f2867b","modified":1604387234076},{"_id":"themes/sb-hitech/layout/includes/third-party/comments/twikoo.pug","hash":"f032eb57f977bbde451b0ec8a826eca14cfca310","modified":1604387234080},{"_id":"themes/sb-hitech/layout/includes/third-party/comments/utterances.pug","hash":"1c7e9fe86b7d7ef18cc876dfce19263fd4e73066","modified":1604387234082},{"_id":"themes/sb-hitech/layout/includes/third-party/comments/valine.pug","hash":"e7da739cabc885eaf4de28e9e6294e4c6b78349d","modified":1604387234084},{"_id":"themes/sb-hitech/layout/includes/third-party/math/index.pug","hash":"0322d640fd6a91853dec3ad39cc24c9b1291322b","modified":1604387234115},{"_id":"themes/sb-hitech/layout/includes/third-party/math/katex.pug","hash":"60bd18e051a442d5ce25325a55982922ab15be04","modified":1604387234119},{"_id":"themes/sb-hitech/layout/includes/third-party/math/mathjax.pug","hash":"6f92311afe60ca5f44055016db9cecce8fb2dc62","modified":1604387234155},{"_id":"themes/sb-hitech/layout/includes/third-party/math/mermaid.pug","hash":"ecb54cd040fa3648ee84f91988073e336a6ec4b8","modified":1604387234158},{"_id":"themes/sb-hitech/layout/includes/third-party/newest-comments/disqus-comment.pug","hash":"2e1cb17c2a95aedf354150a25f2911648e9301cf","modified":1604387234162},{"_id":"themes/sb-hitech/layout/includes/third-party/newest-comments/github-issues.pug","hash":"30e188776865bc9646db3b423c39fd1629390147","modified":1604387234166},{"_id":"themes/sb-hitech/layout/includes/third-party/newest-comments/index.pug","hash":"659f2c0798cf4dbc934508de69bdc05348db7690","modified":1604387234168},{"_id":"themes/sb-hitech/layout/includes/third-party/newest-comments/leancloud.pug","hash":"a5b5eddd1165ddde539c41c5b4183d5dfd82c79b","modified":1604387234171},{"_id":"themes/sb-hitech/layout/includes/third-party/search/algolia.pug","hash":"1c06e60b120c946c1856904848ceba6ab58d1f82","modified":1604387234180},{"_id":"themes/sb-hitech/layout/includes/third-party/search/index.pug","hash":"ff3727c3ec698ec61a28c55cbc8c8508f0efb0a0","modified":1604387234183},{"_id":"themes/sb-hitech/layout/includes/third-party/search/local-search.pug","hash":"598b54746a86878717306a00bfb2613277526a79","modified":1604387234185},{"_id":"themes/sb-hitech/layout/includes/third-party/share/add-this.pug","hash":"8b4034e53ca5bf85097f681a6e76a53ce685c205","modified":1604387234189},{"_id":"themes/sb-hitech/layout/includes/third-party/share/addtoany.pug","hash":"fbac21a6c5924fb2f8d1190fd634105fdbc603d4","modified":1604387234191},{"_id":"themes/sb-hitech/layout/includes/third-party/share/index.pug","hash":"0622e955f3d2efef457f61d0cec0408376bd180a","modified":1604387234193},{"_id":"themes/sb-hitech/layout/includes/third-party/share/share-js.pug","hash":"ee17bb1905b007ce445817efa84e04d7b70467a8","modified":1604387234197},{"_id":"themes/sb-hitech/source/css/_highlight/highlight/diff.styl","hash":"ba3bdf02a6c78b15eada95638173a11445dac7ac","modified":1604387234374},{"_id":"themes/sb-hitech/source/css/_highlight/highlight/index.styl","hash":"1b2dc0ef768c9be9f18d1c1f93d88f916482c5df","modified":1604387234376},{"_id":"themes/sb-hitech/source/css/_highlight/prismjs/diff.styl","hash":"1309292f1c8c53d96cd7333507b106bcc24ca8fc","modified":1604387234381},{"_id":"themes/sb-hitech/source/css/_highlight/prismjs/index.styl","hash":"ebae44a37ac143f4e35523ebd6809371958fb930","modified":1604387234383},{"_id":"themes/sb-hitech/source/css/_highlight/prismjs/line-number.styl","hash":"c1747b8641303a1d9472ec94f2bc654885feb270","modified":1604387234385},{"_id":"source/_posts/ja/Resume/Resume_Shubin_Sun_JA_PR_20201201.pdf","hash":"a721e8bbd64bbe37bc5423bef20efd2520c3fd3c","modified":1606886094493},{"_id":"source/_posts/ja/Resume/Resume_Shubin_Sun_JA_履歴書_20201201.pdf","hash":"8e7097495b52665ebe1cb144ddec7f4ca579e558","modified":1606885946234},{"_id":"source/_posts/ja/Resume/Resume_Shubin_Sun_JA_履歴書_20210101.pdf","hash":"8c75d75dcf3d121e9b369aea5043f01ce312bc47","modified":1606036703317},{"_id":"source/assets/img/top/5.jpg","hash":"d03904a6f52902a55257a56082e115eac702b208","modified":1604387394853},{"_id":"source/assets/img/top/6.jpg","hash":"8047bf92ed861c472cb56a663bfca37fdb75fa42","modified":1604387394853},{"_id":"source/_posts/ja/Resume/Resume_Shubin_Sun_JA_PR_20200901.pdf","hash":"58c5cebcb9323927ad0038d2546ce59d35a80c8f","modified":1604759707826},{"_id":"source/_posts/ja/Resume/Resume_Shubin_Sun_JA_PR_20201001.pdf","hash":"3e716c406dd6825733d7c1912f89aa8022e14a0e","modified":1604759769698},{"_id":"source/_posts/ja/Resume/Resume_Shubin_Sun_JA_PR_20201101.pdf","hash":"db227c5c52a29d91cd404a44727342c6bfe32de7","modified":1606885530846},{"_id":"source/_posts/ja/Resume/Resume_Shubin_Sun_JA_スキルシート_20210101.pdf","hash":"7c28f0086abad481bce01a2b753048457b44fcd9","modified":1606197668163},{"_id":"source/_posts/ja/Resume/Resume_Shubin_Sun_JA_スキルシート_20201201.pdf","hash":"0592f3b679941a1135cac3f06837477c3c22d4d3","modified":1604387394611},{"_id":"source/_posts/ja/Resume/Resume_Shubin_Sun_JA_履歴書_20201101.pdf","hash":"1eaf99a625048194bc8034086b6ee8b8353059e6","modified":1606884977681},{"_id":"source/_posts/ja/Resume/Resume_Shubin_Sun_JA_職務経歴書_20201001.pdf","hash":"312bc30eccc65e0b74050388079d1c678815c904","modified":1604387394673},{"_id":"source/_posts/ja/Resume/Resume_Shubin_Sun_JA_職務経歴書_20201201.pdf","hash":"031d2eaa1fdbc9d25fec4dcada77d9af0f460244","modified":1606886576053},{"_id":"source/_posts/ja/Resume/Resume_Shubin_Sun_JA_職務経歴書_20210101.pdf","hash":"c794bc0a6d80d309cb32fdcf5e33285daf6bf7c6","modified":1606197146297},{"_id":"source/assets/img/top/1.jpg","hash":"d78e5353db65e5f96663ebf17fff3e83032726a9","modified":1604387394833},{"_id":"source/assets/img/top/2.jpg","hash":"de5f02d0660b52c1dae14fbda8130151ac8afe95","modified":1604387394833},{"_id":"source/assets/img/top/4.jpg","hash":"90371c8f9098a727486785c9a7ed87c5e371b529","modified":1604387394843},{"_id":"source/_posts/ja/Resume/Resume_Shubin_Sun_JA_職務経歴書_20200901.pdf","hash":"295ece103ea928f4e6b939c74fd7a1bf3b7aef49","modified":1604387394663},{"_id":"source/_posts/ja/Resume/Resume_Shubin_Sun_JA_履歴書_20200901.pdf","hash":"ead9a4925b97c1f43b3374fd406710cfa2761b9c","modified":1604636903355},{"_id":"source/_posts/ja/Resume/Resume_Shubin_Sun_JA_履歴書_20201001.pdf","hash":"1cada24cebbc94e78e334e92dbf7e8d4f471f0ef","modified":1604636738631},{"_id":"source/_posts/ja/Resume/Resume_Shubin_Sun_JA_職務経歴書_20201101.pdf","hash":"00d151f3a0ff46b066d96f44a18cd02e652095f7","modified":1606885696286},{"_id":"source/_posts/ja/Resume/Resume_Shubin_Sun_JA_強み_20201001.pdf","hash":"8e00b004e1d2cf0be93fd82b3d801e5ea2e13409","modified":1604387394653},{"_id":"source/assets/img/top/9.jpg","hash":"9a427e0d714b5aabce69136a34c89a76c710b883","modified":1604387394873},{"_id":"source/_posts/ja/Resume/Resume_Shubin_Sun_JA_強み_20201101.pdf","hash":"d6e83d22c799446f280cab4c1b18fe9da9370475","modified":1606885607029},{"_id":"source/_posts/ja/Resume/Resume_Shubin_Sun_JA_キャリアプラン_20201201.pdf","hash":"24a952150fc1ab66b40cecbf2b29705f696c4167","modified":1604387394595},{"_id":"source/_posts/ja/Resume/Resume_Shubin_Sun_JA_強み_20210101.pdf","hash":"84271857d2aee4a4281b926c9cb63c8fa46ceff8","modified":1606196871274},{"_id":"source/_posts/ja/Resume/Resume_Shubin_Sun_JA_強み_20201201.pdf","hash":"b3e35fa51f9ce68bcb0a992ec9975add04953835","modified":1606886426417},{"_id":"source/_posts/ja/Resume/Resume_Shubin_Sun_JA_キャリアプラン_20210101.pdf","hash":"84271857d2aee4a4281b926c9cb63c8fa46ceff8","modified":1606196871274},{"_id":"public/index.html","hash":"51ae78380ac1ab652cbc7db2d57c7ad771c7da4d","modified":1607000963968},{"_id":"public/about/index.html","hash":"948080ef99e1e5ba752c0bf51c504a8e92263f4e","modified":1607000963968},{"_id":"public/business-policy/index.html","hash":"fc8e0e7af335b8cb20c4603756120bfe71313645","modified":1607000963968},{"_id":"public/categories/index.html","hash":"def645fee6b64caeeb060769eb6374521860f9b6","modified":1607000963968},{"_id":"public/copyright-policy/index.html","hash":"4a41b1f2bdc07e4d021a3f06e93ef43a1bf01a12","modified":1607000963968},{"_id":"public/link/index.html","hash":"58c1e992cb69ccfda16cdb0872e460b8654b8e92","modified":1607000963968},{"_id":"public/movies/index.html","hash":"d893810b4db10fff169e18894793f39b76f5281b","modified":1607000963968},{"_id":"public/music/index.html","hash":"c8b3c59071ca46065e91e37c3477867f7983f2c7","modified":1607000963968},{"_id":"public/privacy-policy/index.html","hash":"db75a06d2914989557c50baaa059a082f1525ad0","modified":1607000963968},{"_id":"public/tags/index.html","hash":"cb427d0c6508e987f20bc6a3cf83e4df26a51824","modified":1607000963968},{"_id":"public/ja/Resume/Resume/index.html","hash":"1d746efd0fb3c6b88fc52808133c7df432d0e71f","modified":1607000963968},{"_id":"public/archives/index.html","hash":"568e963df154ce361fccf810089b1a12fd76b5c9","modified":1607000963968},{"_id":"public/archives/2020/index.html","hash":"75499201b8448b130817b47823a98d06ed73d56a","modified":1607000963968},{"_id":"public/archives/2020/06/index.html","hash":"0a61b7275057d155cdfa443bbbc96aeadd639e20","modified":1607000963968},{"_id":"public/categories/Resume/index.html","hash":"b69e43558b980f6710b938df3fc3127f42c3232b","modified":1607000963968},{"_id":"public/ja/index.html","hash":"9c4a03af06f0afa15328b78d6a76592400e64045","modified":1607000963968},{"_id":"public/en/index.html","hash":"030c4196669658b40b94672129c589fee69ab6d6","modified":1607000963968},{"_id":"public/kr/index.html","hash":"9eed82adca465c8b357bf390b24f51a9a1162bcb","modified":1607000963968},{"_id":"public/ja/about/index.html","hash":"01e23c857923a540436eae439c8b34de2260e534","modified":1607000963968},{"_id":"public/en/about/index.html","hash":"88c0136ef1ddc16fcbc9d4a7836fcbcbfd6945f5","modified":1607000963968},{"_id":"public/kr/about/index.html","hash":"c4e5507463ca59960817b8d98a704cef71b669b4","modified":1607000963968},{"_id":"public/ja/business-policy/index.html","hash":"e2e94f7b3974107b2f523eb69e776449ef792030","modified":1607000963968},{"_id":"public/en/business-policy/index.html","hash":"440ea2a5fc738affb7991bbe530c1e084e544fcf","modified":1607000963968},{"_id":"public/kr/business-policy/index.html","hash":"86be29ab6f9fede3fdaf5b436e269c8216244942","modified":1607000963968},{"_id":"public/ja/categories/index.html","hash":"edebef838fc587892dab84f0d7e66a2d9eb747fd","modified":1607000963968},{"_id":"public/en/categories/index.html","hash":"62b2a8c3422d133f9e3e31d5190f51a4db1aa4de","modified":1607000963968},{"_id":"public/kr/categories/index.html","hash":"320755aa561e4cead3616df8bde02e30fb455a6a","modified":1607000963968},{"_id":"public/ja/copyright-policy/index.html","hash":"d07e640410576bac91e9e4709b2588ba6166b699","modified":1607000963968},{"_id":"public/en/copyright-policy/index.html","hash":"7347168b218dea5d5167ec6d330ea0652b67e751","modified":1607000963968},{"_id":"public/kr/copyright-policy/index.html","hash":"441cb8a3d57a210448a2fe80935434c94782ba3a","modified":1607000963968},{"_id":"public/ja/link/index.html","hash":"163949863eabac2bbe03ecef319fe935a01141d3","modified":1607000963968},{"_id":"public/en/link/index.html","hash":"a0635e07234716dab6d2f03be81b90032101ee25","modified":1607000963968},{"_id":"public/kr/link/index.html","hash":"0d47fb07991d1cb0952fe8956debb19acb1c7eb1","modified":1607000963968},{"_id":"public/ja/movies/index.html","hash":"fe6e4bb9ef84daa63a4f8ef038976577e272d74d","modified":1607000963968},{"_id":"public/en/movies/index.html","hash":"b2674ae821ca6756bf3e3ca0a840f8a136445670","modified":1607000963968},{"_id":"public/kr/movies/index.html","hash":"6243b551a15fb3bc6866668240474865b8d49856","modified":1607000963968},{"_id":"public/ja/music/index.html","hash":"65322b3ebe27fb77a519adc3de7c17b9a2208c87","modified":1607000963968},{"_id":"public/en/music/index.html","hash":"a43f230d624f0335e44df6d5e5f95c00e73d2031","modified":1607000963968},{"_id":"public/kr/music/index.html","hash":"986b1232670e5c1cde022cb332752c0bc5c4097c","modified":1607000963968},{"_id":"public/ja/privacy-policy/index.html","hash":"2133b66390629551cd617ad43b33a1fca0a13113","modified":1607000963968},{"_id":"public/en/privacy-policy/index.html","hash":"ae65ae73ffa63a13cbe2ff1cb2c77dded3f2c66e","modified":1607000963968},{"_id":"public/kr/privacy-policy/index.html","hash":"9ab946d8a7cea78a4d1594b42c5974c6b2ae28b0","modified":1607000963968},{"_id":"public/ja/tags/index.html","hash":"5d1a97c5cc1c57e03af2ed8c3226d8965dcc77eb","modified":1607000963968},{"_id":"public/en/tags/index.html","hash":"c6c5e4b51a497bc30b8a664146cf3cb44c678a42","modified":1607000963968},{"_id":"public/kr/tags/index.html","hash":"fb9fe638f5a79b38744bba95c9511da21215fd58","modified":1607000963968},{"_id":"public/ja/categories/Resume/index.html","hash":"9bbd15e039bc99742f284f061c03d7f5e1700617","modified":1607000963968},{"_id":"public/en/categories/Resume/index.html","hash":"813dd7a48523755602d4113fa3b49e268d67a1a6","modified":1607000963968},{"_id":"public/kr/categories/Resume/index.html","hash":"e80de43ad1c9515556baa37b2addd9395f03d221","modified":1607000963968},{"_id":"public/ja/archives/index.html","hash":"aa7ada568ea0c2b9a8797ea47e14f85c598c59e5","modified":1607000963968},{"_id":"public/en/archives/index.html","hash":"619db1d61185e5393bb3aaa423fbd8f14c845df6","modified":1607000963968},{"_id":"public/kr/archives/index.html","hash":"c68c464cbe245f6ef1c867e9bf39bed1ff880d7f","modified":1607000963968},{"_id":"public/ja/archives/2020/index.html","hash":"af73d20c72d874a7492930e6af08b939c8307084","modified":1607000963968},{"_id":"public/en/archives/2020/index.html","hash":"ee594a75df04319fe02032fff4f51dde2a8c47a3","modified":1607000963968},{"_id":"public/kr/archives/2020/index.html","hash":"4d8bbb9ffd666a32b3d457dd554c1bbe5a1ac4b5","modified":1607000963968},{"_id":"public/ja/archives/2020/06/index.html","hash":"4f0b82fbeefdea5ddf8d810757236cb8908d59bd","modified":1607000963968},{"_id":"public/en/archives/2020/06/index.html","hash":"8f02844dbbb593d1b517eab348a97967d717c7dd","modified":1607000963968},{"_id":"public/kr/archives/2020/06/index.html","hash":"f2e029bf302d55e83eb74a5bc72b36e31fd4baee","modified":1607000963968},{"_id":"public/tags/個人履歴/index.html","hash":"9b593e4d384fd9724129a096b93319dab3acbf78","modified":1607000963968},{"_id":"public/img/404.jpg","hash":"fb4489bc1d30c93d28f7332158c1c6c1416148de","modified":1607000963968},{"_id":"public/img/algolia.svg","hash":"45eeea0b5fba833e21e38ea10ed5ab385ceb4f01","modified":1607000963968},{"_id":"public/img/favicon.png","hash":"3cf89864b4f6c9b532522a4d260a2e887971c92d","modified":1607000963968},{"_id":"public/img/icp.png","hash":"cb1fd69b38ec23ce8366668ddffbbd0160de0104","modified":1607000963968},{"_id":"public/img/loading.gif","hash":"5f0287fb8fb98872fe1998c6f781111819e71806","modified":1607000963968},{"_id":"public/assets/img/NHK.jpg","hash":"7b4510f981f51b1104b40efa1e352aa996921708","modified":1607000963968},{"_id":"public/assets/img/Portraits.png","hash":"279a3004e12e0489fc21727117aa6655a1f9819b","modified":1607000963968},{"_id":"public/assets/img/favicon.jpg","hash":"7007a1189813e264177c4ef89b61b2ba22adc9a6","modified":1607000963968},{"_id":"public/assets/img/QQ/208934208 MF-COBOL招聘求职.PNG","hash":"1bad87f77de71d04f70029ef2b591e9c29e55a1f","modified":1607000963968},{"_id":"public/assets/img/QQ/212264777对日软件开发国内转职.png","hash":"7a614fdc54eed1ed838163a8bd69777d8df959d2","modified":1607000963968},{"_id":"public/assets/img/QQ/288460606 双创政策与产业园孵化.png","hash":"d4989012114a67165f1e9f088013c5565d0369b9","modified":1607000963968},{"_id":"public/assets/img/QQ/330490168EDUBlockchain Basics.png","hash":"6ef2be030d1ef8df7ddcd9801ad22d25b7b0bc7d","modified":1607000963968},{"_id":"public/assets/img/QQ/330511118创业·就职·公司交流 - 副本.png","hash":"a21d50ca6d12d3fcacb7199ce3960801f4af2a24","modified":1607000963968},{"_id":"public/assets/img/QQ/330511118创业·就职·公司交流.png","hash":"87bd19e9e5df264a2ab16af27dc74c79d9f1fc3f","modified":1607000963968},{"_id":"public/assets/img/QQ/404380953.png","hash":"9cb4d4ed8fdfc7e8fc3ddd2f17faf982ee5ca58d","modified":1607000963968},{"_id":"public/assets/img/QQ/445340268EDUBigData Basics.png","hash":"dd14fac59d62afa50c68d6f90c8fed10c6584231","modified":1607000963968},{"_id":"public/assets/img/QQ/461886087 EDUSalesforce Basics.png","hash":"a17ad7ad7c608927398362b966c48c5594cbd349","modified":1607000963968},{"_id":"public/assets/img/QQ/68280758 上海财经大学研究生.png","hash":"ecda46ecd209240d9abe1c7eb439e24fea19df6c","modified":1607000963968},{"_id":"public/assets/img/QQ/72287061 复旦大学研究生.png","hash":"42875f61890bcce9e9f096443e7ec973b76452f0","modified":1607000963968},{"_id":"public/assets/img/QQ/73017515 西南财经大学研究生.png","hash":"31f6e56871c15689c2389495f007c6360d09d940","modified":1607000963968},{"_id":"public/assets/img/QQ/Salesforce开发@智跃职前实训群聊二维码.png","hash":"fd47d9cd84e42c7ae995608be699e80b13331523","modified":1607000963968},{"_id":"public/assets/img/QQ/大连东软信息学院本科群聊二维码.png","hash":"f93c6d6e19b346e4c07484fd7b52151086f1f5e8","modified":1607000963968},{"_id":"public/assets/img/QQ/大连理工大学本科群聊二维码.png","hash":"a0777e92aedc9f96df4efee1014477c44b1c40be","modified":1607000963968},{"_id":"public/assets/img/QQ/大连理工大学研究生群聊二维码.png","hash":"02360b2cc975224cbe6b3f919506d6554989f869","modified":1607000963968},{"_id":"public/assets/img/QQ/日本语学习交流@智跃职前实训群聊二维码.png","hash":"4326e037bc6ce0789fefd9fcd122ca770b9c9b65","modified":1607000963968},{"_id":"public/assets/img/QQ/智跃书店会员申请02群聊二维码 - 副本.png","hash":"fa7506fdef2cfcd2d28ee9067dfda7c887fb8802","modified":1607000963968},{"_id":"public/assets/img/QQ/智跃书店会员申请02群聊二维码.png","hash":"c6117b22920ef4481aadc169aafa69b291cedc6e","modified":1607000963968},{"_id":"public/assets/img/QQ/ＮＨＫニュース2017下群聊二维码.png","hash":"6f5a8bcdfd8cde2cd83d4583704c459daa42ee49","modified":1607000963968},{"_id":"public/assets/img/QQ/ＮＨＫニュース2018上群聊二维码.png","hash":"dcab28446e552b3e32beb25463b888dcd00724de","modified":1607000963968},{"_id":"public/assets/img/top/3.jpg","hash":"3af041668a04939ea051dec6a911148ca6e5c46b","modified":1607000963968},{"_id":"public/img/friend_404.gif","hash":"8d2d0ebef70a8eb07329f57e645889b0e420fa48","modified":1607000963968},{"_id":"public/assets/img/WeChatPay.jpg","hash":"e02421797e0c699c728604eea5c60c5b759132d1","modified":1607000963968},{"_id":"public/assets/img/dingding/dingding-circle-study.jpg","hash":"acff588ecda7439ce6ce57640eea4e6bd5e6343b","modified":1607000963968},{"_id":"public/assets/img/dingding/dingding-circle-learning.jpg","hash":"cae36f3016bca8bac52c9eec97606272e9f4e548","modified":1607000963968},{"_id":"public/assets/img/dingding/dingding-circle-career.jpg","hash":"d0f520565b6b411b1359d528d2cafac5581aec47","modified":1607000963968},{"_id":"public/assets/img/dingding/dingding-group-excle-rpa.jpg","hash":"5ab1379a028d35802b22233b9b1f462a8d05bd52","modified":1607000963968},{"_id":"public/assets/img/dingding/dingding-group-itjapanese-practice.jpg","hash":"ed260c7b2c5df51bd9c89c7e8bc327acd8e80d87","modified":1607000963968},{"_id":"public/assets/img/dingding/dingding-group-help.jpg","hash":"1f600bf2396e7f78f7390a090de306c373e6d2b3","modified":1607000963968},{"_id":"public/assets/img/dingding/dingding-group-japanese-music.jpg","hash":"ed10115f89ea6531fb34264aecdfbe8787662b49","modified":1607000963968},{"_id":"public/assets/img/dingding/dingding-group-life.jpg","hash":"858eda31e4b17a8fc778c7a75645f312293763f7","modified":1607000963968},{"_id":"public/assets/img/dingding/dingding-group-mainframe.jpg","hash":"28800f6679f6ec8ee223ff5b7dc3bea63a6066ca","modified":1607000963968},{"_id":"public/assets/img/dingding/dingding-group-salesforce.jpg","hash":"09e6aacad1ec3d12a34d282835c820e2c7f98981","modified":1607000963968},{"_id":"public/assets/img/dingding/dingding-group-resume-homepage.jpg","hash":"0e5f5eb7de70a3942d7c947a772045eb35fa83a2","modified":1607000963968},{"_id":"public/assets/img/top/7.jpg","hash":"f7cda1c0c09731ef8bb2e2cb1c299e0529a08e78","modified":1607000963968},{"_id":"public/assets/img/top/8.jpg","hash":"8e1ea131267d6898a4fbdfb85ee57d57d9b96481","modified":1607000963968},{"_id":"public/css/index.css","hash":"9cfcb4ea4e04ae8791b6948412b0a098d4046ec8","modified":1607000963968},{"_id":"public/css/var.css","hash":"da39a3ee5e6b4b0d3255bfef95601890afd80709","modified":1607000963968},{"_id":"public/js/utils.js","hash":"f24426cd3c20057ecf46a872f748bece3fb9653a","modified":1607000963968},{"_id":"public/js/search/algolia.js","hash":"4bc8047817a3a0c11df8409399d57913d713a2a6","modified":1607000963968},{"_id":"public/js/search/local-search.js","hash":"92f2c4c651264331fa7d03e96e79bda4fd0f87db","modified":1607000963968},{"_id":"public/assets/img/top/5.jpg","hash":"d03904a6f52902a55257a56082e115eac702b208","modified":1607000963968},{"_id":"public/assets/img/top/6.jpg","hash":"8047bf92ed861c472cb56a663bfca37fdb75fa42","modified":1607000963968},{"_id":"public/ja/Resume/Resume/Resume_Shubin_Sun_JA_PR_20201001.pdf","hash":"3e716c406dd6825733d7c1912f89aa8022e14a0e","modified":1607000963968},{"_id":"public/ja/Resume/Resume/Resume_Shubin_Sun_JA_PR_20210101.pdf","hash":"4c3af1f358859af086a8c1c93be608d808b2b91d","modified":1607000963968},{"_id":"public/ja/Resume/Resume/Resume_Shubin_Sun_JA_PR_20201201.pdf","hash":"a721e8bbd64bbe37bc5423bef20efd2520c3fd3c","modified":1607000963968},{"_id":"public/ja/Resume/Resume/Resume_Shubin_Sun_JA_履歴書_20201201.pdf","hash":"8e7097495b52665ebe1cb144ddec7f4ca579e558","modified":1607000963968},{"_id":"public/ja/Resume/Resume/Resume_Shubin_Sun_JA_履歴書_20210101.pdf","hash":"8c75d75dcf3d121e9b369aea5043f01ce312bc47","modified":1607000963968},{"_id":"public/js/main.js","hash":"f72262242c4f0e4ae9027b5e291583dff7adc1b2","modified":1607000963968},{"_id":"public/js/tw_cn.js","hash":"2eafc44f4a5b24bef836b00dfc4360a84edb8dcc","modified":1607000963968},{"_id":"public/assets/img/dingding/dingding-group-business-it.jpg","hash":"7fcc5d15171d6e37a00c52bd91d2739f15208369","modified":1607000963968},{"_id":"public/assets/img/top/1.jpg","hash":"d78e5353db65e5f96663ebf17fff3e83032726a9","modified":1607000963968},{"_id":"public/assets/img/top/2.jpg","hash":"de5f02d0660b52c1dae14fbda8130151ac8afe95","modified":1607000963968},{"_id":"public/assets/img/top/4.jpg","hash":"90371c8f9098a727486785c9a7ed87c5e371b529","modified":1607000963968},{"_id":"public/ja/Resume/Resume/Resume_Shubin_Sun_JA_PR_20201101.pdf","hash":"db227c5c52a29d91cd404a44727342c6bfe32de7","modified":1607000963968},{"_id":"public/ja/Resume/Resume/Resume_Shubin_Sun_JA_スキルシート_20201201.pdf","hash":"0592f3b679941a1135cac3f06837477c3c22d4d3","modified":1607000963968},{"_id":"public/ja/Resume/Resume/Resume_Shubin_Sun_JA_職務経歴書_20201001.pdf","hash":"312bc30eccc65e0b74050388079d1c678815c904","modified":1607000963968},{"_id":"public/ja/Resume/Resume/Resume_Shubin_Sun_JA_職務経歴書_20201201.pdf","hash":"031d2eaa1fdbc9d25fec4dcada77d9af0f460244","modified":1607000963968},{"_id":"public/ja/Resume/Resume/Resume_Shubin_Sun_JA_スキルシート_20210101.pdf","hash":"7c28f0086abad481bce01a2b753048457b44fcd9","modified":1607000963968},{"_id":"public/ja/Resume/Resume/Resume_Shubin_Sun_JA_履歴書_20201101.pdf","hash":"1eaf99a625048194bc8034086b6ee8b8353059e6","modified":1607000963968},{"_id":"public/ja/Resume/Resume/Resume_Shubin_Sun_JA_職務経歴書_20200901.pdf","hash":"295ece103ea928f4e6b939c74fd7a1bf3b7aef49","modified":1607000963968},{"_id":"public/ja/Resume/Resume/Resume_Shubin_Sun_JA_職務経歴書_20210101.pdf","hash":"c794bc0a6d80d309cb32fdcf5e33285daf6bf7c6","modified":1607000963968},{"_id":"public/ja/Resume/Resume/Resume_Shubin_Sun_JA_PR_20200901.pdf","hash":"58c5cebcb9323927ad0038d2546ce59d35a80c8f","modified":1607000963968},{"_id":"public/ja/Resume/Resume/Resume_Shubin_Sun_JA_履歴書_20201001.pdf","hash":"1cada24cebbc94e78e334e92dbf7e8d4f471f0ef","modified":1607000963968},{"_id":"public/ja/Resume/Resume/Resume_Shubin_Sun_JA_強み_20201001.pdf","hash":"8e00b004e1d2cf0be93fd82b3d801e5ea2e13409","modified":1607000963968},{"_id":"public/ja/Resume/Resume/Resume_Shubin_Sun_JA_職務経歴書_20201101.pdf","hash":"00d151f3a0ff46b066d96f44a18cd02e652095f7","modified":1607000963968},{"_id":"public/ja/Resume/Resume/Resume_Shubin_Sun_JA_履歴書_20200901.pdf","hash":"ead9a4925b97c1f43b3374fd406710cfa2761b9c","modified":1607000963968},{"_id":"public/assets/img/top/9.jpg","hash":"9a427e0d714b5aabce69136a34c89a76c710b883","modified":1607000963968},{"_id":"public/ja/Resume/Resume/Resume_Shubin_Sun_JA_強み_20201101.pdf","hash":"d6e83d22c799446f280cab4c1b18fe9da9370475","modified":1607000963968},{"_id":"public/ja/Resume/Resume/Resume_Shubin_Sun_JA_キャリアプラン_20201201.pdf","hash":"24a952150fc1ab66b40cecbf2b29705f696c4167","modified":1607000963968},{"_id":"public/ja/Resume/Resume/Resume_Shubin_Sun_JA_強み_20210101.pdf","hash":"84271857d2aee4a4281b926c9cb63c8fa46ceff8","modified":1607000963968},{"_id":"public/ja/Resume/Resume/Resume_Shubin_Sun_JA_キャリアプラン_20210101.pdf","hash":"84271857d2aee4a4281b926c9cb63c8fa46ceff8","modified":1607000963968},{"_id":"public/ja/Resume/Resume/Resume_Shubin_Sun_JA_強み_20201201.pdf","hash":"b3e35fa51f9ce68bcb0a992ec9975add04953835","modified":1607000963968}],"Category":[{"name":"Resume","_id":"cki8uwcdo000bqsbhctg07u65"}],"Data":[],"Page":[{"title":"categories","date":"2020-07-12T03:42:32.000Z","_content":"","source":"index.md","raw":"---\ntitle: categories\ndate: 2020-07-12 12:42:32\n---\n","updated":"2020-11-03T07:09:54.883Z","path":"index.html","comments":1,"layout":"page","_id":"cki8uwcby0000qsbhbzt12g6p","content":"","site":{"data":{}},"cover":"/assets/img/top/5.jpg","excerpt":"","more":""},{"layout":"page","lang":"zh-CN","title":"个人简介","comments":0,"toc":true,"_content":"\n\n2020年9月から　個人のGitHub（https://github.com/sunshubin/）に最新の情報を公開しています。\t\t\t\t\t\t\t\t\t\t\t\t\t\t\t\t\t\t\t\t\t\t\t\t\t\t\t\t\t\t\t\n\t\t\t\t\t\t\t\t\t\t\t\t\t\t\t\t\t\t\t\t\t\t\t\t\t\t\t\t\t\t\t\n履歴書、職務経歴書及び別紙の内容は情報の提供のみを目的としています。情報は更新日のものを掲載していますのでご利用時には変更されている場合もあります。したがって、本資料を用いた運用は必ず自身の責任と判断によって行ってください。これらの情報の運用の結果について 著者はいかなる責任も負けいません。  \t\t\t\t\t\t\t\t\t\t\t\t\t\t\t\t\t\t\t\t\t\t\t\t\t\t\t\t\t\t\t\n\t\t\t\t\t\t\t\t\t\t\t\t\t\t\t\t\t\t\t\t\t\t\t\t\t\t\t\t\t\t\t\n\t\t\t\t\t\t\t\t\t\t\t\t\t\t\t\t\t\t\t\t\t\t\t\t\t\t\t\t\t\t\t\n\t\t\t\t\t\t\t\t\t\t\t\t\t\t\t\t\t\t\t\t\t\t\t\t\t\t\t\t\t\t\t\n資料の一部または全部を著作権法の定める範囲を越え、無断で複写、複製、転載、テープ化、ファイルにおとすことを禁じます。\t\t\t\t\t\t\t\t\t\t\t\t\t\t\t\t\t\t\t\t\t\t\t\t\t\t\t\t\t\t\t\n\t\t\t\t\t\t\t\t\t\t\t\t\t\t\t\t\t\t\t\t\t\t\t\t\t\t\t\t\t\t\t\n","source":"about/index.md","raw":"---\nlayout: page\nlang: zh-CN\ntitle: 个人简介\ncomments: false\ntoc: true\n---\n\n\n2020年9月から　個人のGitHub（https://github.com/sunshubin/）に最新の情報を公開しています。\t\t\t\t\t\t\t\t\t\t\t\t\t\t\t\t\t\t\t\t\t\t\t\t\t\t\t\t\t\t\t\n\t\t\t\t\t\t\t\t\t\t\t\t\t\t\t\t\t\t\t\t\t\t\t\t\t\t\t\t\t\t\t\n履歴書、職務経歴書及び別紙の内容は情報の提供のみを目的としています。情報は更新日のものを掲載していますのでご利用時には変更されている場合もあります。したがって、本資料を用いた運用は必ず自身の責任と判断によって行ってください。これらの情報の運用の結果について 著者はいかなる責任も負けいません。  \t\t\t\t\t\t\t\t\t\t\t\t\t\t\t\t\t\t\t\t\t\t\t\t\t\t\t\t\t\t\t\n\t\t\t\t\t\t\t\t\t\t\t\t\t\t\t\t\t\t\t\t\t\t\t\t\t\t\t\t\t\t\t\n\t\t\t\t\t\t\t\t\t\t\t\t\t\t\t\t\t\t\t\t\t\t\t\t\t\t\t\t\t\t\t\n\t\t\t\t\t\t\t\t\t\t\t\t\t\t\t\t\t\t\t\t\t\t\t\t\t\t\t\t\t\t\t\n資料の一部または全部を著作権法の定める範囲を越え、無断で複写、複製、転載、テープ化、ファイルにおとすことを禁じます。\t\t\t\t\t\t\t\t\t\t\t\t\t\t\t\t\t\t\t\t\t\t\t\t\t\t\t\t\t\t\t\n\t\t\t\t\t\t\t\t\t\t\t\t\t\t\t\t\t\t\t\t\t\t\t\t\t\t\t\t\t\t\t\n","date":"2020-11-03T14:36:31.429Z","updated":"2020-11-03T07:09:54.703Z","path":"about/index.html","_id":"cki8uwccb0001qsbhd4y8e0zo","content":"<p>2020年9月から　個人のGitHub（<a href=\"https://github.com/sunshubin/%EF%BC%89%E3%81%AB%E6%9C%80%E6%96%B0%E3%81%AE%E6%83%85%E5%A0%B1%E3%82%92%E5%85%AC%E9%96%8B%E3%81%97%E3%81%A6%E3%81%84%E3%81%BE%E3%81%99%E3%80%82\">https://github.com/sunshubin/）に最新の情報を公開しています。</a>                                                                                                                            </p>\n<p>履歴書、職務経歴書及び別紙の内容は情報の提供のみを目的としています。情報は更新日のものを掲載していますのでご利用時には変更されている場合もあります。したがって、本資料を用いた運用は必ず自身の責任と判断によって行ってください。これらの情報の運用の結果について 著者はいかなる責任も負けいません。                                                                                                                              </p>\n<p>資料の一部または全部を著作権法の定める範囲を越え、無断で複写、複製、転載、テープ化、ファイルにおとすことを禁じます。                                                                                                                            </p>\n","site":{"data":{}},"cover":"/assets/img/top/6.jpg","excerpt":"","more":"<p>2020年9月から　個人のGitHub（<a href=\"https://github.com/sunshubin/%EF%BC%89%E3%81%AB%E6%9C%80%E6%96%B0%E3%81%AE%E6%83%85%E5%A0%B1%E3%82%92%E5%85%AC%E9%96%8B%E3%81%97%E3%81%A6%E3%81%84%E3%81%BE%E3%81%99%E3%80%82\">https://github.com/sunshubin/）に最新の情報を公開しています。</a>                                                                                                                            </p>\n<p>履歴書、職務経歴書及び別紙の内容は情報の提供のみを目的としています。情報は更新日のものを掲載していますのでご利用時には変更されている場合もあります。したがって、本資料を用いた運用は必ず自身の責任と判断によって行ってください。これらの情報の運用の結果について 著者はいかなる責任も負けいません。                                                                                                                              </p>\n<p>資料の一部または全部を著作権法の定める範囲を越え、無断で複写、複製、転載、テープ化、ファイルにおとすことを禁じます。                                                                                                                            </p>\n"},{"title":"Business policy","date":"2020-07-13T07:05:38.000Z","_content":"","source":"business-policy/index.md","raw":"---\ntitle: Business policy\ndate: 2020-07-13 16:05:38\n---\n","updated":"2020-11-03T07:09:54.883Z","path":"business-policy/index.html","comments":1,"layout":"page","_id":"cki8uwcce0002qsbh3lvqd4wm","content":"","site":{"data":{}},"cover":"/assets/img/top/4.jpg","excerpt":"","more":""},{"title":"分类","date":"2018-01-04T15:00:00.000Z","lang":"zh-CN","type":"categories","_content":"","source":"categories/index.md","raw":"---\ntitle: 分类\ndate: 2018-01-05 00:00:00\nlang: zh-CN\ntype: \"categories\"\n---\n","updated":"2020-11-03T07:09:54.883Z","path":"categories/index.html","comments":1,"layout":"page","_id":"cki8uwccj0003qsbh3hqe6kaa","content":"","site":{"data":{}},"cover":"/assets/img/top/3.jpg","excerpt":"","more":""},{"layout":"page","title":"知识产权与免责声明","lang":"zh-CN","comments":0,"toc":true,"date":"2018-08-13T09:18:18.000Z","updated":"2020-10-10T09:58:58.000Z","_content":"\n\n# 站点介绍   \n\n|域名|内容介绍|\n|--:|:--|\nsb-hrms.com|人力资源开发与职业能力测评系统演示版\nsb-hrbp.com|面向企业的人力资源服务外包系统演示版\nsb-hitech.github.io|内部项目研发代码库\nsb-talents.github.io|学习教程与知识库\nsb-recruit.github.io|猎头服务与招聘信息\nsunshubin.github.io|个人主页\n    \n<br>\n\n# 微信公众号\n\n公众号名称|所属|内容简介\n:---:|:--:|:--\n考研留学与就职|个人|主要推送先进技术知识分享\n幸福的职业生涯|个人|职场常识，法律以及劳动争议对策\n大连智桥科技有限公司的人工智能|企业|不定期推送与人工智能、教育技术、心理学等领域相关br的文章  \n\n<br>\n\n# 社交软件\n在企业微信、钉钉、GitHub等平台开设有群组，请参阅相关介绍文章    <br>\n\n# 知识产权声明     \n网站、微信公众平台、企业微信、钉钉、GitHub等平台已声明的原创文章，将由大连智桥科技有限公司享有其知识产权。    \n大连智桥科技有限公司，目前暂未对外营业。\n\n<br>\n\n# 免责声明    \n第三方机构或个人如想转载作者文章，包括但不限于发布于微信公众号(三个公众号：考研留学与就职、幸福的职业生涯、人工智能)、网站、GitHub资料库及，团队成员个人主页及关联存储库内的资源，均请原文转载（不得修改）。    <br>\n如文章内容有改动，须在发布前获得原作者或者团队的审核批准。同时，请必须在文章内附以下信息及免责声明：    <br>\n本资料中所含内容乃一般性信息，作者及团队并不因此构成提供任何专业建议或服务。作者及团队均不对任何方因使用本资料而导致的任何损失承担责任。   \n\n<br>\n\n# 特别声明\n任何有涉嫌违法及违背社会公德的行为的组织和个人，我们谢绝一切往来。  \n<br>   \n\n# 联系方式\n咨询邮箱：info@sb-hrbp.com    \n\n# 更新履历\n\n|版本号|更新要点|更新日期|\n|:---|:---|---:|\n|1.0.1.2|修订|20200808|\n|1.0.0.1|内容初版|20200707|\n\n<br>\n\n","source":"copyright-policy/index.md","raw":"---\nlayout: page\ntitle: 知识产权与免责声明\nlang: zh-CN\ncomments: false\ntoc: true\ndate: 2018-08-13 18:18:18\nupdated: 2020-10-10 18:58:58\n---\n\n\n# 站点介绍   \n\n|域名|内容介绍|\n|--:|:--|\nsb-hrms.com|人力资源开发与职业能力测评系统演示版\nsb-hrbp.com|面向企业的人力资源服务外包系统演示版\nsb-hitech.github.io|内部项目研发代码库\nsb-talents.github.io|学习教程与知识库\nsb-recruit.github.io|猎头服务与招聘信息\nsunshubin.github.io|个人主页\n    \n<br>\n\n# 微信公众号\n\n公众号名称|所属|内容简介\n:---:|:--:|:--\n考研留学与就职|个人|主要推送先进技术知识分享\n幸福的职业生涯|个人|职场常识，法律以及劳动争议对策\n大连智桥科技有限公司的人工智能|企业|不定期推送与人工智能、教育技术、心理学等领域相关br的文章  \n\n<br>\n\n# 社交软件\n在企业微信、钉钉、GitHub等平台开设有群组，请参阅相关介绍文章    <br>\n\n# 知识产权声明     \n网站、微信公众平台、企业微信、钉钉、GitHub等平台已声明的原创文章，将由大连智桥科技有限公司享有其知识产权。    \n大连智桥科技有限公司，目前暂未对外营业。\n\n<br>\n\n# 免责声明    \n第三方机构或个人如想转载作者文章，包括但不限于发布于微信公众号(三个公众号：考研留学与就职、幸福的职业生涯、人工智能)、网站、GitHub资料库及，团队成员个人主页及关联存储库内的资源，均请原文转载（不得修改）。    <br>\n如文章内容有改动，须在发布前获得原作者或者团队的审核批准。同时，请必须在文章内附以下信息及免责声明：    <br>\n本资料中所含内容乃一般性信息，作者及团队并不因此构成提供任何专业建议或服务。作者及团队均不对任何方因使用本资料而导致的任何损失承担责任。   \n\n<br>\n\n# 特别声明\n任何有涉嫌违法及违背社会公德的行为的组织和个人，我们谢绝一切往来。  \n<br>   \n\n# 联系方式\n咨询邮箱：info@sb-hrbp.com    \n\n# 更新履历\n\n|版本号|更新要点|更新日期|\n|:---|:---|---:|\n|1.0.1.2|修订|20200808|\n|1.0.0.1|内容初版|20200707|\n\n<br>\n\n","path":"copyright-policy/index.html","_id":"cki8uwccm0004qsbhf3is43ra","content":"<h1 id=\"站点介绍\"><a href=\"#站点介绍\" class=\"headerlink\" title=\"站点介绍\"></a>站点介绍</h1><table>\n<thead>\n<tr>\n<th align=\"right\">域名</th>\n<th align=\"left\">内容介绍</th>\n</tr>\n</thead>\n<tbody><tr>\n<td align=\"right\">sb-hrms.com</td>\n<td align=\"left\">人力资源开发与职业能力测评系统演示版</td>\n</tr>\n<tr>\n<td align=\"right\">sb-hrbp.com</td>\n<td align=\"left\">面向企业的人力资源服务外包系统演示版</td>\n</tr>\n<tr>\n<td align=\"right\">sb-hitech.github.io</td>\n<td align=\"left\">内部项目研发代码库</td>\n</tr>\n<tr>\n<td align=\"right\">sb-talents.github.io</td>\n<td align=\"left\">学习教程与知识库</td>\n</tr>\n<tr>\n<td align=\"right\">sb-recruit.github.io</td>\n<td align=\"left\">猎头服务与招聘信息</td>\n</tr>\n<tr>\n<td align=\"right\">sunshubin.github.io</td>\n<td align=\"left\">个人主页</td>\n</tr>\n</tbody></table>\n<br>\n\n<h1 id=\"微信公众号\"><a href=\"#微信公众号\" class=\"headerlink\" title=\"微信公众号\"></a>微信公众号</h1><table>\n<thead>\n<tr>\n<th align=\"center\">公众号名称</th>\n<th align=\"center\">所属</th>\n<th align=\"left\">内容简介</th>\n</tr>\n</thead>\n<tbody><tr>\n<td align=\"center\">考研留学与就职</td>\n<td align=\"center\">个人</td>\n<td align=\"left\">主要推送先进技术知识分享</td>\n</tr>\n<tr>\n<td align=\"center\">幸福的职业生涯</td>\n<td align=\"center\">个人</td>\n<td align=\"left\">职场常识，法律以及劳动争议对策</td>\n</tr>\n<tr>\n<td align=\"center\">大连智桥科技有限公司的人工智能</td>\n<td align=\"center\">企业</td>\n<td align=\"left\">不定期推送与人工智能、教育技术、心理学等领域相关br的文章</td>\n</tr>\n</tbody></table>\n<br>\n\n<h1 id=\"社交软件\"><a href=\"#社交软件\" class=\"headerlink\" title=\"社交软件\"></a>社交软件</h1><p>在企业微信、钉钉、GitHub等平台开设有群组，请参阅相关介绍文章    <br></p>\n<h1 id=\"知识产权声明\"><a href=\"#知识产权声明\" class=\"headerlink\" title=\"知识产权声明\"></a>知识产权声明</h1><p>网站、微信公众平台、企业微信、钉钉、GitHub等平台已声明的原创文章，将由大连智桥科技有限公司享有其知识产权。<br>大连智桥科技有限公司，目前暂未对外营业。</p>\n<br>\n\n<h1 id=\"免责声明\"><a href=\"#免责声明\" class=\"headerlink\" title=\"免责声明\"></a>免责声明</h1><p>第三方机构或个人如想转载作者文章，包括但不限于发布于微信公众号(三个公众号：考研留学与就职、幸福的职业生涯、人工智能)、网站、GitHub资料库及，团队成员个人主页及关联存储库内的资源，均请原文转载（不得修改）。    <br><br>如文章内容有改动，须在发布前获得原作者或者团队的审核批准。同时，请必须在文章内附以下信息及免责声明：    <br><br>本资料中所含内容乃一般性信息，作者及团队并不因此构成提供任何专业建议或服务。作者及团队均不对任何方因使用本资料而导致的任何损失承担责任。   </p>\n<br>\n\n<h1 id=\"特别声明\"><a href=\"#特别声明\" class=\"headerlink\" title=\"特别声明\"></a>特别声明</h1><p>任何有涉嫌违法及违背社会公德的行为的组织和个人，我们谢绝一切往来。<br><br>   </p>\n<h1 id=\"联系方式\"><a href=\"#联系方式\" class=\"headerlink\" title=\"联系方式\"></a>联系方式</h1><p>咨询邮箱：<a href=\"mailto:&#105;&#110;&#x66;&#111;&#x40;&#x73;&#x62;&#45;&#x68;&#x72;&#98;&#112;&#46;&#x63;&#111;&#109;\">&#105;&#110;&#x66;&#111;&#x40;&#x73;&#x62;&#45;&#x68;&#x72;&#98;&#112;&#46;&#x63;&#111;&#109;</a>    </p>\n<h1 id=\"更新履历\"><a href=\"#更新履历\" class=\"headerlink\" title=\"更新履历\"></a>更新履历</h1><table>\n<thead>\n<tr>\n<th align=\"left\">版本号</th>\n<th align=\"left\">更新要点</th>\n<th align=\"right\">更新日期</th>\n</tr>\n</thead>\n<tbody><tr>\n<td align=\"left\">1.0.1.2</td>\n<td align=\"left\">修订</td>\n<td align=\"right\">20200808</td>\n</tr>\n<tr>\n<td align=\"left\">1.0.0.1</td>\n<td align=\"left\">内容初版</td>\n<td align=\"right\">20200707</td>\n</tr>\n</tbody></table>\n<br>\n\n","site":{"data":{}},"cover":"/assets/img/top/7.jpg","excerpt":"","more":"<h1 id=\"站点介绍\"><a href=\"#站点介绍\" class=\"headerlink\" title=\"站点介绍\"></a>站点介绍</h1><table>\n<thead>\n<tr>\n<th align=\"right\">域名</th>\n<th align=\"left\">内容介绍</th>\n</tr>\n</thead>\n<tbody><tr>\n<td align=\"right\">sb-hrms.com</td>\n<td align=\"left\">人力资源开发与职业能力测评系统演示版</td>\n</tr>\n<tr>\n<td align=\"right\">sb-hrbp.com</td>\n<td align=\"left\">面向企业的人力资源服务外包系统演示版</td>\n</tr>\n<tr>\n<td align=\"right\">sb-hitech.github.io</td>\n<td align=\"left\">内部项目研发代码库</td>\n</tr>\n<tr>\n<td align=\"right\">sb-talents.github.io</td>\n<td align=\"left\">学习教程与知识库</td>\n</tr>\n<tr>\n<td align=\"right\">sb-recruit.github.io</td>\n<td align=\"left\">猎头服务与招聘信息</td>\n</tr>\n<tr>\n<td align=\"right\">sunshubin.github.io</td>\n<td align=\"left\">个人主页</td>\n</tr>\n</tbody></table>\n<br>\n\n<h1 id=\"微信公众号\"><a href=\"#微信公众号\" class=\"headerlink\" title=\"微信公众号\"></a>微信公众号</h1><table>\n<thead>\n<tr>\n<th align=\"center\">公众号名称</th>\n<th align=\"center\">所属</th>\n<th align=\"left\">内容简介</th>\n</tr>\n</thead>\n<tbody><tr>\n<td align=\"center\">考研留学与就职</td>\n<td align=\"center\">个人</td>\n<td align=\"left\">主要推送先进技术知识分享</td>\n</tr>\n<tr>\n<td align=\"center\">幸福的职业生涯</td>\n<td align=\"center\">个人</td>\n<td align=\"left\">职场常识，法律以及劳动争议对策</td>\n</tr>\n<tr>\n<td align=\"center\">大连智桥科技有限公司的人工智能</td>\n<td align=\"center\">企业</td>\n<td align=\"left\">不定期推送与人工智能、教育技术、心理学等领域相关br的文章</td>\n</tr>\n</tbody></table>\n<br>\n\n<h1 id=\"社交软件\"><a href=\"#社交软件\" class=\"headerlink\" title=\"社交软件\"></a>社交软件</h1><p>在企业微信、钉钉、GitHub等平台开设有群组，请参阅相关介绍文章    <br></p>\n<h1 id=\"知识产权声明\"><a href=\"#知识产权声明\" class=\"headerlink\" title=\"知识产权声明\"></a>知识产权声明</h1><p>网站、微信公众平台、企业微信、钉钉、GitHub等平台已声明的原创文章，将由大连智桥科技有限公司享有其知识产权。<br>大连智桥科技有限公司，目前暂未对外营业。</p>\n<br>\n\n<h1 id=\"免责声明\"><a href=\"#免责声明\" class=\"headerlink\" title=\"免责声明\"></a>免责声明</h1><p>第三方机构或个人如想转载作者文章，包括但不限于发布于微信公众号(三个公众号：考研留学与就职、幸福的职业生涯、人工智能)、网站、GitHub资料库及，团队成员个人主页及关联存储库内的资源，均请原文转载（不得修改）。    <br><br>如文章内容有改动，须在发布前获得原作者或者团队的审核批准。同时，请必须在文章内附以下信息及免责声明：    <br><br>本资料中所含内容乃一般性信息，作者及团队并不因此构成提供任何专业建议或服务。作者及团队均不对任何方因使用本资料而导致的任何损失承担责任。   </p>\n<br>\n\n<h1 id=\"特别声明\"><a href=\"#特别声明\" class=\"headerlink\" title=\"特别声明\"></a>特别声明</h1><p>任何有涉嫌违法及违背社会公德的行为的组织和个人，我们谢绝一切往来。<br><br>   </p>\n<h1 id=\"联系方式\"><a href=\"#联系方式\" class=\"headerlink\" title=\"联系方式\"></a>联系方式</h1><p>咨询邮箱：<a href=\"mailto:&#105;&#110;&#x66;&#111;&#x40;&#x73;&#x62;&#45;&#x68;&#x72;&#98;&#112;&#46;&#x63;&#111;&#109;\">&#105;&#110;&#x66;&#111;&#x40;&#x73;&#x62;&#45;&#x68;&#x72;&#98;&#112;&#46;&#x63;&#111;&#109;</a>    </p>\n<h1 id=\"更新履历\"><a href=\"#更新履历\" class=\"headerlink\" title=\"更新履历\"></a>更新履历</h1><table>\n<thead>\n<tr>\n<th align=\"left\">版本号</th>\n<th align=\"left\">更新要点</th>\n<th align=\"right\">更新日期</th>\n</tr>\n</thead>\n<tbody><tr>\n<td align=\"left\">1.0.1.2</td>\n<td align=\"left\">修订</td>\n<td align=\"right\">20200808</td>\n</tr>\n<tr>\n<td align=\"left\">1.0.0.1</td>\n<td align=\"left\">内容初版</td>\n<td align=\"right\">20200707</td>\n</tr>\n</tbody></table>\n<br>\n\n"},{"layout":"page","title":"友情链接","date":"2018-06-07T13:17:49.000Z","type":"link","_content":"\n\n","source":"link/index.md","raw":"---\nlayout: page\ntitle: 友情链接\ndate: 2018-06-07 22:17:49\ntype: \"link\"\n---\n\n\n","updated":"2020-11-04T01:35:35.680Z","path":"link/index.html","comments":1,"_id":"cki8uwccp0005qsbha8usd488","content":"","site":{"data":{}},"cover":"/assets/img/top/4.jpg","excerpt":"","more":""},{"title":"视频","date":"2018-06-07T13:17:49.000Z","type":"movies","_content":"\n\n","source":"movies/index.md","raw":"---\ntitle: 视频\ndate: 2018-06-07 22:17:49\ntype: movies\n---\n\n\n","updated":"2020-11-03T07:09:54.893Z","path":"movies/index.html","comments":1,"layout":"page","_id":"cki8uwccs0006qsbh0fixga1t","content":"","site":{"data":{}},"cover":"/assets/img/top/7.jpg","excerpt":"","more":""},{"title":"音乐","date":"2018-06-07T13:17:49.000Z","type":"music","_content":"\n\n","source":"music/index.md","raw":"---\ntitle: 音乐\ndate: 2018-06-07 22:17:49\ntype: music\n---\n\n\n","updated":"2020-11-03T07:09:54.893Z","path":"music/index.html","comments":1,"layout":"page","_id":"cki8uwccu0007qsbha5a743qp","content":"","site":{"data":{}},"cover":"/assets/img/top/5.jpg","excerpt":"","more":""},{"title":"Privacy policy","date":"2020-07-13T07:05:38.000Z","_content":"","source":"privacy-policy/index.md","raw":"---\ntitle: Privacy policy\ndate: 2020-07-13 16:05:38\n---\n","updated":"2020-11-03T07:09:54.903Z","path":"privacy-policy/index.html","comments":1,"layout":"page","_id":"cki8uwccy0008qsbhflmzeux4","content":"","site":{"data":{}},"cover":"/assets/img/top/1.jpg","excerpt":"","more":""},{"title":"标签","date":"2018-01-04T15:00:00.000Z","type":"tags","_content":"\n\n","source":"tags/index.md","raw":"---\ntitle: 标签\ndate: 2018-01-05 00:00:00\ntype: \"tags\"\n---\n\n\n","updated":"2020-11-03T07:09:54.903Z","path":"tags/index.html","comments":1,"layout":"page","_id":"cki8uwcd60009qsbh3rmh96zi","content":"","site":{"data":{}},"cover":"/assets/img/top/1.jpg","excerpt":"","more":""}],"Post":[{"title":"個人履歴","authors":"Sun Shubin","lang":"ja","sticky":88888888,"toc":true,"comments":0,"abbrlink":38496,"date":"2020-06-30T09:13:50.000Z","updated":"2021-01-01T09:58:58.000Z","_content":"　　\n# 個人履歴\n\n**提示**  \n- このページの書類は　ソーシャル繋がりのために　公開しました。 \n- このページの書類は 一部個人の興味・関心・将来みたい仕事の内容を記入しました。汎用版なので　応募職位の業務知識と能力について　面談・面接の場合　詳しい説明します。 \n- このページは常に1ヶ月ほど　更新しています。**太い字書類**は面接用なバージョンです。メール「sunshubin@outlook.jp」で連絡して　正式な書類を送付いたします。 \n  \n|Update|Resume|PR|Strong|Experience|Skill|PPT|Video|Version\n---|:---:|:--:|:---:|:---:|:---:|:---:|---|:---:\n---|---|---|---|---|---|---|---|---\n2022/01/01|---|---|---|---|---|---|---|---\n2021/10/01|---|---|---|---|---|---|---|---\n2021/07/01|---|---|---|---|<a href=\"./Resume_Shubin_Sun_JA_スキルシート_20201201.pdf\" title=\"スキルチェックシートをダウンロード\"  target=\"_blank\">スキルシート</a>|---|---|作成中\n2021/04/01|---|---|---|---|---|---|---|∝\n2021/01/01|---|---|---|---|---|---|---|阝\n**2020/12/01**|<a href=\"./Resume_Shubin_Sun_JA_履歴書_20201201.pdf\" title=\"履歴書をダウンロード\"  target=\"_blank\">履歴書</a>|<a href=\"./Resume_Shubin_Sun_JA_PR_20201201.pdf\" title=\"PRをダウンロード\"  target=\"_blank\">PR</a>|<a href=\"./Resume_Shubin_Sun_JA_強み_20201201.pdf\" title=\"強みをダウンロード\"  target=\"_blank\">強み</a>|<a href=\"./Resume_Shubin_Sun_JA_職務経歴書_20201201.pdf\" title=\"職務経歴書をダウンロード\"  target=\"_blank\">職務経歴書</a> |---|---|---|**4.11.16.113**\n2020/11/01|<a href=\"./Resume_Shubin_Sun_JA_履歴書_20201101.pdf\" title=\"履歴書をダウンロード\"  target=\"_blank\">履歴書</a>|<a href=\"./Resume_Shubin_Sun_JA_PR_20201101.pdf\" title=\"PRをダウンロード\"  target=\"_blank\">PR</a>|<a href=\"./Resume_Shubin_Sun_JA_強み_20201101.pdf\" title=\"強みをダウンロード\"  target=\"_blank\">強み</a>|<a href=\"./Resume_Shubin_Sun_JA_職務経歴書_20201101.pdf\" title=\"職務経歴書をダウンロード\"  target=\"_blank\">職務経歴書</a> |---|---|---|4.11.10.106\n2020/10/01|<a href=\"./Resume_Shubin_Sun_JA_履歴書_20201001.pdf\" title=\"履歴書をダウンロード\"  target=\"_blank\">履歴書</a>|<a href=\"./Resume_Shubin_Sun_JA_PR_20201001.pdf\" title=\"PRをダウンロード\"  target=\"_blank\">PR</a>|<a href=\"./Resume_Shubin_Sun_JA_強み_20201001.pdf\" title=\"強みをダウンロード\"  target=\"_blank\">強み</a>|<a href=\"./Resume_Shubin_Sun_JA_職務経歴書_20201001.pdf\" title=\"職務経歴書をダウンロード\"  target=\"_blank\">職務経歴書</a> |---|---|---|4.9.10.101\n2020/09/01|<a href=\"./Resume_Shubin_Sun_JA_履歴書_20200901.pdf\" title=\"履歴書をダウンロード\"  target=\"_blank\">履歴書</a>|<a href=\"./Resume_Shubin_Sun_JA_PR_20200901.pdf\" title=\"PRをダウンロード\"  target=\"_blank\">PR</a>|---|<a href=\"./Resume_Shubin_Sun_JA_職務経歴書_20200901.pdf\" title=\"職務経歴書をダウンロード\"  target=\"_blank\">職務経歴書</a>|---|---|---|4.3.5.50\n---|---|---|---|---|---|---|---|---\n---|---|---|---|---|---|---|---|---\n    \n   　\nVersion：【フォーマット変更】.【内容変更】.【ミス修正】.【ファイル保存回数】","source":"_posts/ja/Resume.md","raw":"---\ntitle: 個人履歴\nauthors: Sun Shubin\nlang: ja\nsticky: 88888888\ntoc: true\ncomments: false\ncategories:\n  - Resume\ntags:\n  - 個人履歴\nabbrlink: 38496\ndate: 2020-06-30 18:13:50\nupdated: 2021-01-01 18:58:58\n---\n　　\n# 個人履歴\n\n**提示**  \n- このページの書類は　ソーシャル繋がりのために　公開しました。 \n- このページの書類は 一部個人の興味・関心・将来みたい仕事の内容を記入しました。汎用版なので　応募職位の業務知識と能力について　面談・面接の場合　詳しい説明します。 \n- このページは常に1ヶ月ほど　更新しています。**太い字書類**は面接用なバージョンです。メール「sunshubin@outlook.jp」で連絡して　正式な書類を送付いたします。 \n  \n|Update|Resume|PR|Strong|Experience|Skill|PPT|Video|Version\n---|:---:|:--:|:---:|:---:|:---:|:---:|---|:---:\n---|---|---|---|---|---|---|---|---\n2022/01/01|---|---|---|---|---|---|---|---\n2021/10/01|---|---|---|---|---|---|---|---\n2021/07/01|---|---|---|---|<a href=\"./Resume_Shubin_Sun_JA_スキルシート_20201201.pdf\" title=\"スキルチェックシートをダウンロード\"  target=\"_blank\">スキルシート</a>|---|---|作成中\n2021/04/01|---|---|---|---|---|---|---|∝\n2021/01/01|---|---|---|---|---|---|---|阝\n**2020/12/01**|<a href=\"./Resume_Shubin_Sun_JA_履歴書_20201201.pdf\" title=\"履歴書をダウンロード\"  target=\"_blank\">履歴書</a>|<a href=\"./Resume_Shubin_Sun_JA_PR_20201201.pdf\" title=\"PRをダウンロード\"  target=\"_blank\">PR</a>|<a href=\"./Resume_Shubin_Sun_JA_強み_20201201.pdf\" title=\"強みをダウンロード\"  target=\"_blank\">強み</a>|<a href=\"./Resume_Shubin_Sun_JA_職務経歴書_20201201.pdf\" title=\"職務経歴書をダウンロード\"  target=\"_blank\">職務経歴書</a> |---|---|---|**4.11.16.113**\n2020/11/01|<a href=\"./Resume_Shubin_Sun_JA_履歴書_20201101.pdf\" title=\"履歴書をダウンロード\"  target=\"_blank\">履歴書</a>|<a href=\"./Resume_Shubin_Sun_JA_PR_20201101.pdf\" title=\"PRをダウンロード\"  target=\"_blank\">PR</a>|<a href=\"./Resume_Shubin_Sun_JA_強み_20201101.pdf\" title=\"強みをダウンロード\"  target=\"_blank\">強み</a>|<a href=\"./Resume_Shubin_Sun_JA_職務経歴書_20201101.pdf\" title=\"職務経歴書をダウンロード\"  target=\"_blank\">職務経歴書</a> |---|---|---|4.11.10.106\n2020/10/01|<a href=\"./Resume_Shubin_Sun_JA_履歴書_20201001.pdf\" title=\"履歴書をダウンロード\"  target=\"_blank\">履歴書</a>|<a href=\"./Resume_Shubin_Sun_JA_PR_20201001.pdf\" title=\"PRをダウンロード\"  target=\"_blank\">PR</a>|<a href=\"./Resume_Shubin_Sun_JA_強み_20201001.pdf\" title=\"強みをダウンロード\"  target=\"_blank\">強み</a>|<a href=\"./Resume_Shubin_Sun_JA_職務経歴書_20201001.pdf\" title=\"職務経歴書をダウンロード\"  target=\"_blank\">職務経歴書</a> |---|---|---|4.9.10.101\n2020/09/01|<a href=\"./Resume_Shubin_Sun_JA_履歴書_20200901.pdf\" title=\"履歴書をダウンロード\"  target=\"_blank\">履歴書</a>|<a href=\"./Resume_Shubin_Sun_JA_PR_20200901.pdf\" title=\"PRをダウンロード\"  target=\"_blank\">PR</a>|---|<a href=\"./Resume_Shubin_Sun_JA_職務経歴書_20200901.pdf\" title=\"職務経歴書をダウンロード\"  target=\"_blank\">職務経歴書</a>|---|---|---|4.3.5.50\n---|---|---|---|---|---|---|---|---\n---|---|---|---|---|---|---|---|---\n    \n   　\nVersion：【フォーマット変更】.【内容変更】.【ミス修正】.【ファイル保存回数】","slug":"Resume","published":1,"layout":"post","photos":[],"link":"","_id":"cki8uwcd8000aqsbhgtrd5178","content":"<p>　　</p>\n<h1 id=\"個人履歴\"><a href=\"#個人履歴\" class=\"headerlink\" title=\"個人履歴\"></a>個人履歴</h1><p><strong>提示</strong>  </p>\n<ul>\n<li>このページの書類は　ソーシャル繋がりのために　公開しました。 </li>\n<li>このページの書類は 一部個人の興味・関心・将来みたい仕事の内容を記入しました。汎用版なので　応募職位の業務知識と能力について　面談・面接の場合　詳しい説明します。 </li>\n<li>このページは常に1ヶ月ほど　更新しています。<strong>太い字書類</strong>は面接用なバージョンです。メール「<a href=\"mailto:&#115;&#117;&#x6e;&#115;&#x68;&#117;&#98;&#x69;&#x6e;&#x40;&#111;&#x75;&#x74;&#108;&#x6f;&#111;&#107;&#46;&#106;&#112;\">&#115;&#117;&#x6e;&#115;&#x68;&#117;&#98;&#x69;&#x6e;&#x40;&#111;&#x75;&#x74;&#108;&#x6f;&#111;&#107;&#46;&#106;&#112;</a>」で連絡して　正式な書類を送付いたします。 </li>\n</ul>\n<table>\n<thead>\n<tr>\n<th>Update</th>\n<th align=\"center\">Resume</th>\n<th align=\"center\">PR</th>\n<th align=\"center\">Strong</th>\n<th align=\"center\">Experience</th>\n<th align=\"center\">Skill</th>\n<th align=\"center\">PPT</th>\n<th>Video</th>\n<th align=\"center\">Version</th>\n</tr>\n</thead>\n<tbody><tr>\n<td>—</td>\n<td align=\"center\">—</td>\n<td align=\"center\">—</td>\n<td align=\"center\">—</td>\n<td align=\"center\">—</td>\n<td align=\"center\">—</td>\n<td align=\"center\">—</td>\n<td>—</td>\n<td align=\"center\">—</td>\n</tr>\n<tr>\n<td>2022/01/01</td>\n<td align=\"center\">—</td>\n<td align=\"center\">—</td>\n<td align=\"center\">—</td>\n<td align=\"center\">—</td>\n<td align=\"center\">—</td>\n<td align=\"center\">—</td>\n<td>—</td>\n<td align=\"center\">—</td>\n</tr>\n<tr>\n<td>2021/10/01</td>\n<td align=\"center\">—</td>\n<td align=\"center\">—</td>\n<td align=\"center\">—</td>\n<td align=\"center\">—</td>\n<td align=\"center\">—</td>\n<td align=\"center\">—</td>\n<td>—</td>\n<td align=\"center\">—</td>\n</tr>\n<tr>\n<td>2021/07/01</td>\n<td align=\"center\">—</td>\n<td align=\"center\">—</td>\n<td align=\"center\">—</td>\n<td align=\"center\">—</td>\n<td align=\"center\"><a href=\"./Resume_Shubin_Sun_JA_スキルシート_20201201.pdf\" title=\"スキルチェックシートをダウンロード\"  target=\"_blank\">スキルシート</a></td>\n<td align=\"center\">—</td>\n<td>—</td>\n<td align=\"center\">作成中</td>\n</tr>\n<tr>\n<td>2021/04/01</td>\n<td align=\"center\">—</td>\n<td align=\"center\">—</td>\n<td align=\"center\">—</td>\n<td align=\"center\">—</td>\n<td align=\"center\">—</td>\n<td align=\"center\">—</td>\n<td>—</td>\n<td align=\"center\">∝</td>\n</tr>\n<tr>\n<td>2021/01/01</td>\n<td align=\"center\">—</td>\n<td align=\"center\">—</td>\n<td align=\"center\">—</td>\n<td align=\"center\">—</td>\n<td align=\"center\">—</td>\n<td align=\"center\">—</td>\n<td>—</td>\n<td align=\"center\">阝</td>\n</tr>\n<tr>\n<td><strong>2020/12/01</strong></td>\n<td align=\"center\"><a href=\"./Resume_Shubin_Sun_JA_履歴書_20201201.pdf\" title=\"履歴書をダウンロード\"  target=\"_blank\">履歴書</a></td>\n<td align=\"center\"><a href=\"./Resume_Shubin_Sun_JA_PR_20201201.pdf\" title=\"PRをダウンロード\"  target=\"_blank\">PR</a></td>\n<td align=\"center\"><a href=\"./Resume_Shubin_Sun_JA_強み_20201201.pdf\" title=\"強みをダウンロード\"  target=\"_blank\">強み</a></td>\n<td align=\"center\"><a href=\"./Resume_Shubin_Sun_JA_職務経歴書_20201201.pdf\" title=\"職務経歴書をダウンロード\"  target=\"_blank\">職務経歴書</a></td>\n<td align=\"center\">—</td>\n<td align=\"center\">—</td>\n<td>—</td>\n<td align=\"center\"><strong>4.11.16.113</strong></td>\n</tr>\n<tr>\n<td>2020/11/01</td>\n<td align=\"center\"><a href=\"./Resume_Shubin_Sun_JA_履歴書_20201101.pdf\" title=\"履歴書をダウンロード\"  target=\"_blank\">履歴書</a></td>\n<td align=\"center\"><a href=\"./Resume_Shubin_Sun_JA_PR_20201101.pdf\" title=\"PRをダウンロード\"  target=\"_blank\">PR</a></td>\n<td align=\"center\"><a href=\"./Resume_Shubin_Sun_JA_強み_20201101.pdf\" title=\"強みをダウンロード\"  target=\"_blank\">強み</a></td>\n<td align=\"center\"><a href=\"./Resume_Shubin_Sun_JA_職務経歴書_20201101.pdf\" title=\"職務経歴書をダウンロード\"  target=\"_blank\">職務経歴書</a></td>\n<td align=\"center\">—</td>\n<td align=\"center\">—</td>\n<td>—</td>\n<td align=\"center\">4.11.10.106</td>\n</tr>\n<tr>\n<td>2020/10/01</td>\n<td align=\"center\"><a href=\"./Resume_Shubin_Sun_JA_履歴書_20201001.pdf\" title=\"履歴書をダウンロード\"  target=\"_blank\">履歴書</a></td>\n<td align=\"center\"><a href=\"./Resume_Shubin_Sun_JA_PR_20201001.pdf\" title=\"PRをダウンロード\"  target=\"_blank\">PR</a></td>\n<td align=\"center\"><a href=\"./Resume_Shubin_Sun_JA_強み_20201001.pdf\" title=\"強みをダウンロード\"  target=\"_blank\">強み</a></td>\n<td align=\"center\"><a href=\"./Resume_Shubin_Sun_JA_職務経歴書_20201001.pdf\" title=\"職務経歴書をダウンロード\"  target=\"_blank\">職務経歴書</a></td>\n<td align=\"center\">—</td>\n<td align=\"center\">—</td>\n<td>—</td>\n<td align=\"center\">4.9.10.101</td>\n</tr>\n<tr>\n<td>2020/09/01</td>\n<td align=\"center\"><a href=\"./Resume_Shubin_Sun_JA_履歴書_20200901.pdf\" title=\"履歴書をダウンロード\"  target=\"_blank\">履歴書</a></td>\n<td align=\"center\"><a href=\"./Resume_Shubin_Sun_JA_PR_20200901.pdf\" title=\"PRをダウンロード\"  target=\"_blank\">PR</a></td>\n<td align=\"center\">—</td>\n<td align=\"center\"><a href=\"./Resume_Shubin_Sun_JA_職務経歴書_20200901.pdf\" title=\"職務経歴書をダウンロード\"  target=\"_blank\">職務経歴書</a></td>\n<td align=\"center\">—</td>\n<td align=\"center\">—</td>\n<td>—</td>\n<td align=\"center\">4.3.5.50</td>\n</tr>\n<tr>\n<td>—</td>\n<td align=\"center\">—</td>\n<td align=\"center\">—</td>\n<td align=\"center\">—</td>\n<td align=\"center\">—</td>\n<td align=\"center\">—</td>\n<td align=\"center\">—</td>\n<td>—</td>\n<td align=\"center\">—</td>\n</tr>\n<tr>\n<td>—</td>\n<td align=\"center\">—</td>\n<td align=\"center\">—</td>\n<td align=\"center\">—</td>\n<td align=\"center\">—</td>\n<td align=\"center\">—</td>\n<td align=\"center\">—</td>\n<td>—</td>\n<td align=\"center\">—</td>\n</tr>\n</tbody></table>\n<p>   　<br>Version：【フォーマット変更】.【内容変更】.【ミス修正】.【ファイル保存回数】</p>\n","site":{"data":{}},"cover":"/assets/img/top/4.jpg","excerpt":"","more":"<p>　　</p>\n<h1 id=\"個人履歴\"><a href=\"#個人履歴\" class=\"headerlink\" title=\"個人履歴\"></a>個人履歴</h1><p><strong>提示</strong>  </p>\n<ul>\n<li>このページの書類は　ソーシャル繋がりのために　公開しました。 </li>\n<li>このページの書類は 一部個人の興味・関心・将来みたい仕事の内容を記入しました。汎用版なので　応募職位の業務知識と能力について　面談・面接の場合　詳しい説明します。 </li>\n<li>このページは常に1ヶ月ほど　更新しています。<strong>太い字書類</strong>は面接用なバージョンです。メール「<a href=\"mailto:&#115;&#117;&#x6e;&#115;&#x68;&#117;&#98;&#x69;&#x6e;&#x40;&#111;&#x75;&#x74;&#108;&#x6f;&#111;&#107;&#46;&#106;&#112;\">&#115;&#117;&#x6e;&#115;&#x68;&#117;&#98;&#x69;&#x6e;&#x40;&#111;&#x75;&#x74;&#108;&#x6f;&#111;&#107;&#46;&#106;&#112;</a>」で連絡して　正式な書類を送付いたします。 </li>\n</ul>\n<table>\n<thead>\n<tr>\n<th>Update</th>\n<th align=\"center\">Resume</th>\n<th align=\"center\">PR</th>\n<th align=\"center\">Strong</th>\n<th align=\"center\">Experience</th>\n<th align=\"center\">Skill</th>\n<th align=\"center\">PPT</th>\n<th>Video</th>\n<th align=\"center\">Version</th>\n</tr>\n</thead>\n<tbody><tr>\n<td>—</td>\n<td align=\"center\">—</td>\n<td align=\"center\">—</td>\n<td align=\"center\">—</td>\n<td align=\"center\">—</td>\n<td align=\"center\">—</td>\n<td align=\"center\">—</td>\n<td>—</td>\n<td align=\"center\">—</td>\n</tr>\n<tr>\n<td>2022/01/01</td>\n<td align=\"center\">—</td>\n<td align=\"center\">—</td>\n<td align=\"center\">—</td>\n<td align=\"center\">—</td>\n<td align=\"center\">—</td>\n<td align=\"center\">—</td>\n<td>—</td>\n<td align=\"center\">—</td>\n</tr>\n<tr>\n<td>2021/10/01</td>\n<td align=\"center\">—</td>\n<td align=\"center\">—</td>\n<td align=\"center\">—</td>\n<td align=\"center\">—</td>\n<td align=\"center\">—</td>\n<td align=\"center\">—</td>\n<td>—</td>\n<td align=\"center\">—</td>\n</tr>\n<tr>\n<td>2021/07/01</td>\n<td align=\"center\">—</td>\n<td align=\"center\">—</td>\n<td align=\"center\">—</td>\n<td align=\"center\">—</td>\n<td align=\"center\"><a href=\"./Resume_Shubin_Sun_JA_スキルシート_20201201.pdf\" title=\"スキルチェックシートをダウンロード\"  target=\"_blank\">スキルシート</a></td>\n<td align=\"center\">—</td>\n<td>—</td>\n<td align=\"center\">作成中</td>\n</tr>\n<tr>\n<td>2021/04/01</td>\n<td align=\"center\">—</td>\n<td align=\"center\">—</td>\n<td align=\"center\">—</td>\n<td align=\"center\">—</td>\n<td align=\"center\">—</td>\n<td align=\"center\">—</td>\n<td>—</td>\n<td align=\"center\">∝</td>\n</tr>\n<tr>\n<td>2021/01/01</td>\n<td align=\"center\">—</td>\n<td align=\"center\">—</td>\n<td align=\"center\">—</td>\n<td align=\"center\">—</td>\n<td align=\"center\">—</td>\n<td align=\"center\">—</td>\n<td>—</td>\n<td align=\"center\">阝</td>\n</tr>\n<tr>\n<td><strong>2020/12/01</strong></td>\n<td align=\"center\"><a href=\"./Resume_Shubin_Sun_JA_履歴書_20201201.pdf\" title=\"履歴書をダウンロード\"  target=\"_blank\">履歴書</a></td>\n<td align=\"center\"><a href=\"./Resume_Shubin_Sun_JA_PR_20201201.pdf\" title=\"PRをダウンロード\"  target=\"_blank\">PR</a></td>\n<td align=\"center\"><a href=\"./Resume_Shubin_Sun_JA_強み_20201201.pdf\" title=\"強みをダウンロード\"  target=\"_blank\">強み</a></td>\n<td align=\"center\"><a href=\"./Resume_Shubin_Sun_JA_職務経歴書_20201201.pdf\" title=\"職務経歴書をダウンロード\"  target=\"_blank\">職務経歴書</a></td>\n<td align=\"center\">—</td>\n<td align=\"center\">—</td>\n<td>—</td>\n<td align=\"center\"><strong>4.11.16.113</strong></td>\n</tr>\n<tr>\n<td>2020/11/01</td>\n<td align=\"center\"><a href=\"./Resume_Shubin_Sun_JA_履歴書_20201101.pdf\" title=\"履歴書をダウンロード\"  target=\"_blank\">履歴書</a></td>\n<td align=\"center\"><a href=\"./Resume_Shubin_Sun_JA_PR_20201101.pdf\" title=\"PRをダウンロード\"  target=\"_blank\">PR</a></td>\n<td align=\"center\"><a href=\"./Resume_Shubin_Sun_JA_強み_20201101.pdf\" title=\"強みをダウンロード\"  target=\"_blank\">強み</a></td>\n<td align=\"center\"><a href=\"./Resume_Shubin_Sun_JA_職務経歴書_20201101.pdf\" title=\"職務経歴書をダウンロード\"  target=\"_blank\">職務経歴書</a></td>\n<td align=\"center\">—</td>\n<td align=\"center\">—</td>\n<td>—</td>\n<td align=\"center\">4.11.10.106</td>\n</tr>\n<tr>\n<td>2020/10/01</td>\n<td align=\"center\"><a href=\"./Resume_Shubin_Sun_JA_履歴書_20201001.pdf\" title=\"履歴書をダウンロード\"  target=\"_blank\">履歴書</a></td>\n<td align=\"center\"><a href=\"./Resume_Shubin_Sun_JA_PR_20201001.pdf\" title=\"PRをダウンロード\"  target=\"_blank\">PR</a></td>\n<td align=\"center\"><a href=\"./Resume_Shubin_Sun_JA_強み_20201001.pdf\" title=\"強みをダウンロード\"  target=\"_blank\">強み</a></td>\n<td align=\"center\"><a href=\"./Resume_Shubin_Sun_JA_職務経歴書_20201001.pdf\" title=\"職務経歴書をダウンロード\"  target=\"_blank\">職務経歴書</a></td>\n<td align=\"center\">—</td>\n<td align=\"center\">—</td>\n<td>—</td>\n<td align=\"center\">4.9.10.101</td>\n</tr>\n<tr>\n<td>2020/09/01</td>\n<td align=\"center\"><a href=\"./Resume_Shubin_Sun_JA_履歴書_20200901.pdf\" title=\"履歴書をダウンロード\"  target=\"_blank\">履歴書</a></td>\n<td align=\"center\"><a href=\"./Resume_Shubin_Sun_JA_PR_20200901.pdf\" title=\"PRをダウンロード\"  target=\"_blank\">PR</a></td>\n<td align=\"center\">—</td>\n<td align=\"center\"><a href=\"./Resume_Shubin_Sun_JA_職務経歴書_20200901.pdf\" title=\"職務経歴書をダウンロード\"  target=\"_blank\">職務経歴書</a></td>\n<td align=\"center\">—</td>\n<td align=\"center\">—</td>\n<td>—</td>\n<td align=\"center\">4.3.5.50</td>\n</tr>\n<tr>\n<td>—</td>\n<td align=\"center\">—</td>\n<td align=\"center\">—</td>\n<td align=\"center\">—</td>\n<td align=\"center\">—</td>\n<td align=\"center\">—</td>\n<td align=\"center\">—</td>\n<td>—</td>\n<td align=\"center\">—</td>\n</tr>\n<tr>\n<td>—</td>\n<td align=\"center\">—</td>\n<td align=\"center\">—</td>\n<td align=\"center\">—</td>\n<td align=\"center\">—</td>\n<td align=\"center\">—</td>\n<td align=\"center\">—</td>\n<td>—</td>\n<td align=\"center\">—</td>\n</tr>\n</tbody></table>\n<p>   　<br>Version：【フォーマット変更】.【内容変更】.【ミス修正】.【ファイル保存回数】</p>\n"}],"PostAsset":[{"_id":"source/_posts/ja/Resume/Resume_Shubin_Sun_JA_PR_20200901.pdf","post":"cki8uwcd8000aqsbhgtrd5178","slug":"Resume_Shubin_Sun_JA_PR_20200901.pdf","modified":1,"renderable":1},{"_id":"source/_posts/ja/Resume/Resume_Shubin_Sun_JA_PR_20201001.pdf","post":"cki8uwcd8000aqsbhgtrd5178","slug":"Resume_Shubin_Sun_JA_PR_20201001.pdf","modified":1,"renderable":1},{"_id":"source/_posts/ja/Resume/Resume_Shubin_Sun_JA_PR_20201101.pdf","post":"cki8uwcd8000aqsbhgtrd5178","slug":"Resume_Shubin_Sun_JA_PR_20201101.pdf","modified":1,"renderable":1},{"_id":"source/_posts/ja/Resume/Resume_Shubin_Sun_JA_PR_20201201.pdf","post":"cki8uwcd8000aqsbhgtrd5178","slug":"Resume_Shubin_Sun_JA_PR_20201201.pdf","modified":1,"renderable":1},{"_id":"source/_posts/ja/Resume/Resume_Shubin_Sun_JA_PR_20210101.pdf","post":"cki8uwcd8000aqsbhgtrd5178","slug":"Resume_Shubin_Sun_JA_PR_20210101.pdf","modified":1,"renderable":1},{"_id":"source/_posts/ja/Resume/Resume_Shubin_Sun_JA_キャリアプラン_20201201.pdf","post":"cki8uwcd8000aqsbhgtrd5178","slug":"Resume_Shubin_Sun_JA_キャリアプラン_20201201.pdf","modified":1,"renderable":1},{"_id":"source/_posts/ja/Resume/Resume_Shubin_Sun_JA_キャリアプラン_20210101.pdf","post":"cki8uwcd8000aqsbhgtrd5178","slug":"Resume_Shubin_Sun_JA_キャリアプラン_20210101.pdf","modified":1,"renderable":1},{"_id":"source/_posts/ja/Resume/Resume_Shubin_Sun_JA_スキルシート_20201201.pdf","post":"cki8uwcd8000aqsbhgtrd5178","slug":"Resume_Shubin_Sun_JA_スキルシート_20201201.pdf","modified":1,"renderable":1},{"_id":"source/_posts/ja/Resume/Resume_Shubin_Sun_JA_スキルシート_20210101.pdf","post":"cki8uwcd8000aqsbhgtrd5178","slug":"Resume_Shubin_Sun_JA_スキルシート_20210101.pdf","modified":1,"renderable":1},{"_id":"source/_posts/ja/Resume/Resume_Shubin_Sun_JA_履歴書_20200901.pdf","post":"cki8uwcd8000aqsbhgtrd5178","slug":"Resume_Shubin_Sun_JA_履歴書_20200901.pdf","modified":1,"renderable":1},{"_id":"source/_posts/ja/Resume/Resume_Shubin_Sun_JA_履歴書_20201001.pdf","post":"cki8uwcd8000aqsbhgtrd5178","slug":"Resume_Shubin_Sun_JA_履歴書_20201001.pdf","modified":1,"renderable":1},{"_id":"source/_posts/ja/Resume/Resume_Shubin_Sun_JA_履歴書_20201101.pdf","post":"cki8uwcd8000aqsbhgtrd5178","slug":"Resume_Shubin_Sun_JA_履歴書_20201101.pdf","modified":1,"renderable":1},{"_id":"source/_posts/ja/Resume/Resume_Shubin_Sun_JA_履歴書_20201201.pdf","post":"cki8uwcd8000aqsbhgtrd5178","slug":"Resume_Shubin_Sun_JA_履歴書_20201201.pdf","modified":1,"renderable":1},{"_id":"source/_posts/ja/Resume/Resume_Shubin_Sun_JA_履歴書_20210101.pdf","post":"cki8uwcd8000aqsbhgtrd5178","slug":"Resume_Shubin_Sun_JA_履歴書_20210101.pdf","modified":1,"renderable":1},{"_id":"source/_posts/ja/Resume/Resume_Shubin_Sun_JA_強み_20201001.pdf","post":"cki8uwcd8000aqsbhgtrd5178","slug":"Resume_Shubin_Sun_JA_強み_20201001.pdf","modified":1,"renderable":1},{"_id":"source/_posts/ja/Resume/Resume_Shubin_Sun_JA_強み_20201101.pdf","post":"cki8uwcd8000aqsbhgtrd5178","slug":"Resume_Shubin_Sun_JA_強み_20201101.pdf","modified":1,"renderable":1},{"_id":"source/_posts/ja/Resume/Resume_Shubin_Sun_JA_強み_20201201.pdf","post":"cki8uwcd8000aqsbhgtrd5178","slug":"Resume_Shubin_Sun_JA_強み_20201201.pdf","modified":1,"renderable":1},{"_id":"source/_posts/ja/Resume/Resume_Shubin_Sun_JA_強み_20210101.pdf","post":"cki8uwcd8000aqsbhgtrd5178","slug":"Resume_Shubin_Sun_JA_強み_20210101.pdf","modified":1,"renderable":1},{"_id":"source/_posts/ja/Resume/Resume_Shubin_Sun_JA_職務経歴書_20200901.pdf","post":"cki8uwcd8000aqsbhgtrd5178","slug":"Resume_Shubin_Sun_JA_職務経歴書_20200901.pdf","modified":1,"renderable":1},{"_id":"source/_posts/ja/Resume/Resume_Shubin_Sun_JA_職務経歴書_20201001.pdf","post":"cki8uwcd8000aqsbhgtrd5178","slug":"Resume_Shubin_Sun_JA_職務経歴書_20201001.pdf","modified":1,"renderable":1},{"_id":"source/_posts/ja/Resume/Resume_Shubin_Sun_JA_職務経歴書_20201101.pdf","post":"cki8uwcd8000aqsbhgtrd5178","slug":"Resume_Shubin_Sun_JA_職務経歴書_20201101.pdf","modified":1,"renderable":1},{"_id":"source/_posts/ja/Resume/Resume_Shubin_Sun_JA_職務経歴書_20201201.pdf","post":"cki8uwcd8000aqsbhgtrd5178","slug":"Resume_Shubin_Sun_JA_職務経歴書_20201201.pdf","modified":1,"renderable":1},{"_id":"source/_posts/ja/Resume/Resume_Shubin_Sun_JA_職務経歴書_20210101.pdf","post":"cki8uwcd8000aqsbhgtrd5178","slug":"Resume_Shubin_Sun_JA_職務経歴書_20210101.pdf","modified":1,"renderable":1}],"PostCategory":[{"post_id":"cki8uwcd8000aqsbhgtrd5178","category_id":"cki8uwcdo000bqsbhctg07u65","_id":"cki8uwcdz000eqsbhew5t44xa"}],"PostTag":[{"post_id":"cki8uwcd8000aqsbhgtrd5178","tag_id":"cki8uwcdu000cqsbhatf3folc","_id":"cki8uwcdy000dqsbhhucd6s4h"}],"Tag":[{"name":"個人履歴","_id":"cki8uwcdu000cqsbhatf3folc"}]}}